[
  {
    "id": "0066902c-dfbc-4094-82d7-817c1e4533e0",
    "slug": "san-mateo-county-pride-center",
    "externalUrl": "https://sanmateopride.org/",
    "tags": [
      "transmasculine",
      "non-binary",
      "transfeminine",
      "healthcare",
      "mental-health",
      "social-services"
    ],
    "address": "1021 S El Camino Real, San Mateo, CA 94402, USA",
    "phoneNumber": "650-591-0133",
    "country": "US",
    "provinceOrState": "CA",
    "city": "San Mateo",
    "county": "San Mateo County",
    "latLng": [
      37.5569591,
      -122.3189073
    ],
    "socialMedia": {
      "yelpUrl": "https://www.yelp.com/biz/san-mateo-county-pride-center-san-mateo",
      "googleMapsUrl": "https://goo.gl/maps/uj5ogP9y4LboxZYD9",
      "facebookUrl": null,
      "twitterUrl": null,
      "instagramUrl": null,
      "youtubeUrl": null,
      "tiktokUrl": null,
      "twitchUrl": null,
      "patreonUrl": null
    },
    "title": "सॅन माटेओ काउंटी प्राईड सेंटर",
    "description": "सॅन माटेओ काउंटी प्राईड सेंटर ही एक सहकार्याच्या मॉडेल संस्था आणि LGBTQ+ समुदायासाठीची एकूण दुकान आहे. आम्ही सर्व वयोमानांच्या LGBTQ+ समुदायाच्या सदस्यांना समर्थन देणारी चटकामत्वपूर्ण कार्यक्रमे आणि सेवा देतो, ज्यामध्ये शिक्षण, प्रशिक्षण, समुदायीच्या कार्यक्रमांची समावेश, सहकारी समूहांची समर्थन, दैनंदिनी कार्यक्रमे, क्लिनिकल थेरपी, आणि बायकेस कार्य केलेला व्यवस्थापन."
  },
  {
    "id": "04f0d550-7d16-415f-ae3f-51740223c48f",
    "slug": "understanding-and-supporting-transsexuality-in-children-and-parents",
    "externalUrl": "https://www.kinderinfo.de/ratgeber/transsexualitaet/",
    "tags": [
      "transmasculine",
      "transfeminine",
      "youth-services",
      "parent-family-resources",
      "education-awareness"
    ],
    "address": null,
    "phoneNumber": null,
    "country": "DE",
    "provinceOrState": null,
    "city": null,
    "county": null,
    "latLng": null,
    "email": null,
    "socialMedia": null,
    "title": "मुलांच्या आणि पालकांच्या पुलंगलिंगत्वाची समज आणि समर्थन",
    "description": "ही जर्मन लेख मुलांच्या किंवा पालकांच्या पुलंगलिंगत्वासाठी कुटुंबीयांना व्यापक मार्गदर्शिका देते. त्यात महत्त्वाच्या क्रियाकलापांची आणि संसाधनांची माहिती दिली आहे, स्थितीची समज आणि स्वीकारणे पासून सुरु होते ते संबंधित उपचारांची मागणी करण्यासाठी मार्गदर्शन देते."
  },
  {
    "id": "07e16941-b605-4cf5-bab5-bdc882c51a1d",
    "slug": "queerspace",
    "externalUrl": "https://www.queerspace.org.au/",
    "tags": [
      "mental-health",
      "social-services",
      "youth-services",
      "support-groups",
      "parent-family-resources",
      "education-awareness"
    ],
    "address": "100 Drummond St, Carlton VIC 3053, Australia",
    "phoneNumber": "03 9663 6733",
    "country": "AU",
    "provinceOrState": "VIC",
    "city": "Carlton",
    "county": "City of Melbourne",
    "latLng": [
      -37.8043894,
      144.9681606
    ],
    "email": "enquiries@ds.org.au",
    "socialMedia": {
      "yelpUrl": null,
      "googleMapsUrl": null
    },
    "title": "Queerspace",
    "description": "Queerspace हे LGBTIQ+ आरोग्य आणि कल्याण समर्थन सेवा 2009 मध्ये LGBTIQ+ समुदायांनी LGBTIQ+ समुदायांसाठी स्थापन केलेली आहे. त्यात संबंध, कुटुंब, पालनपोषण आणि तरुणांच्या केंद्रभूत धोरणावर मुद्देआहेत व महाराष्ट्राच्या उत्तर-पश्चिम महानगर क्षेत्रातील सेवांची सहस्थानी सेवा देते. सेवांमध्ये सल्लागारी, प्रकरण व्यवस्थापन, पक्षसत्ता, समर्थन सेवा, सहकारी समर्थन, व्यावसायिक विकास, प्रशिक्षण आणि सल्लागारी असतात."
  },
  {
    "id": "0db36ba9-b329-4a54-8302-d7810866457a",
    "slug": "diyhrtcafe",
    "externalUrl": "https://diyhrt.cafe",
    "tags": [
      "transfeminine",
      "non-binary",
      "transmasculine",
      "healthcare",
      "education-awareness"
    ],
    "title": "DIYHRT.cafe",
    "description": "स्वत:ची हॉर्मोन बदलेली उपचार (HRT) करणार्या व्यक्त्यांसाठी एक उज्जवळ ऑनलाईन समुदाय आणि ज्ञानाचे केंद्र. त्यांची वेबसाईट स्वत:च्या HRT साठी माहिती, संसाधने आणि समर्थन मिळवण्याच्या ठिकाणी सुरक्षित आणि समाविष्ट करणारी जागा प्रदान करण्यासमर्पित आहे. किंवा तुम्ही दोसागी पद्धतींची शोध घेतली आहे, डोसाईजिंग आणि प्रशासनासाठी मार्गदर्शन होऊ द्या किंवा फक्त इतरांशी सांगणारे अनुभव्या, DIYHRT.cafe तुमच्या आरोग्य आणि क्षेमाबद्दल सुचेत संपादनांसाठी तुम्हाला मदत करण्यासाठी मूल्यवान अंतर्दृष्टी, व्यक्तिगत कथा आणि तज्ज्ञ सल्ला प्रदान करते."
  },
  {
    "id": "0df181cd-6431-4f05-a79f-6ae5c8e3f79b",
    "slug": "stuttgarter-declaration-gender-self-determined",
    "externalUrl": "https://die-erklaerung.de/",
    "tags": [
      "legal",
      "healthcare",
      "mental-health",
      "education-awareness"
    ],
    "address": null,
    "phoneNumber": null,
    "country": "DE",
    "provinceOrState": "BW",
    "city": "Stuttgart",
    "county": null,
    "latLng": null,
    "email": null,
    "socialMedia": null,
    "title": "स्टुटगर्टर घोषणापत्र: लिंग. स्वत:ची. निर्धारित.",
    "description": "स्टुटगर्टर घोषणापत्रात ट्रान्सजेंडर आणि इंटरसेक्स व्यक्त्यांचा सन्मानपूर्वक वागणूक करण्याच्या महत्त्वाची मुद्रांकिती आहे. यामध्ये ट्रान्सजेंडर आणि इंटरसेक्स व्यक्तींसाठी वैद्यकीय, मनोचिकित्सानिष्ठ, सल्लागारी, आणि सहाय्य सेवांमधील मानवाधिकारांच्या महत्त्वाची मुद्रांकिती करते. याला वैद्यकीय व्यक्ती, मनोचिकित्सक, मानवाधिकार कारवाई करणारे, आणि प्रभावित व्यक्तींनी विकसित केलेल्या, ते आपले स्वत:चे लिंग ठरवण्याचे अधिकार आणि या स्वत:च्या निर्धारितीवर आदर देण्याची वैद्यकीय उपचारांची आवश्यकता यांची मुद्रांकिती करते."
  },
  {
    "id": "11cfde25-5434-4fae-b782-c9597ebe52f3",
    "slug": "deifydeify-qtibipoc-collective",
    "externalUrl": "https://linktr.ee/deifycbr",
    "tags": [
      "social-services",
      "support-groups",
      "community-stories",
      "education-awareness"
    ],
    "address": null,
    "phoneNumber": null,
    "country": null,
    "provinceOrState": null,
    "city": null,
    "county": null,
    "latLng": null,
    "email": null,
    "socialMedia": {
      "facebookUrl": "QTIBIPOC Canberra Facebook Group"
    },
    "title": "DEiFYDEiFYQTIBIPOC संगठन न्गणॉव्हाल, न्गुनवाल आणि न्गांबरी देशात वास्य",
    "description": "ही DEiFYQTIBIPOC समुदायासाठी एक सामूहिक बैठक आहे. समूहाने Queer Masculinities Zine आणि त्यांच्या विशिष्ट प्लेलिस्टविषयीही चर्चा केली जाईल."
  },
  {
    "id": "1665b1de-c17a-4c22-ace3-d635d35ef2b9",
    "slug": "bundesverband-trans",
    "externalUrl": "https://www.bundesverband-trans.de/",
    "tags": [
      "transmasculine",
      "non-binary",
      "transfeminine",
      "legal",
      "healthcare",
      "mental-health",
      "social-services",
      "education-awareness",
      "support-groups"
    ],
    "address": "Prinzregentenstraße 84, 10717 Berlin, Germany",
    "phoneNumber": "+49 (0) 30 – 23 94 98 96",
    "country": "DE",
    "provinceOrState": "BE",
    "city": "Berlin",
    "latLng": [
      52.4890033,
      13.3333558
    ],
    "email": "info@bv-trans.de",
    "socialMedia": null,
    "town": "Bezirk Charlottenburg-Wilmersdorf",
    "title": "Bundesverband Trans* e.V.",
    "description": "Bundesverband Trans* e.V. ही जर्मनीतील ट्रान्स* व्यक्तींच्या हक्कांसाठी संघटनेची एक राष्ट्रीय संस्था आहे, त्यातले ट्रान्ससेक्सुअल, ट्रान्सजेंडर, जेंडरक्विर, नॉन-बायनरी आणि ट्रान्स* म्हणजेच त्यांच्या ओळखीं साठीचे. त्यांचे ध्येय या समुदायासाठीच्या परिस्थितीच्या सुधारणासाठी कायदेशीर, राजकीय आणि वैद्यकीय सुधारणे करणे आहे जे या समुदायाच्या सल्ल्यांसाठी कार्यशाळांचे आयोजन करून, सल्ला देऊन आणि प्रकाशने सार्वजनिक करून मिळवलेले आहे."
  },
  {
    "id": "1873eb7a-2dcb-4346-bf6b-91a97237072f",
    "slug": "nsw-service-for-the-treatment-and-rehabilitation-of-torture-and-trauma-survivors",
    "externalUrl": "https://www.startts.org.au/",
    "tags": [
      "healthcare",
      "mental-health",
      "social-services"
    ],
    "phoneNumber": "+61 (0)2 9646 6700",
    "country": "AU",
    "provinceOrState": "NSW",
    "city": "Carramar",
    "address": "152/168 The Horsley Dr, Carramar NSW 2163, Australia",
    "latLng": [
      -33.8801011,
      150.9654668
    ],
    "email": "stts-startts@health.nsw.gov.au",
    "socialMedia": {
      "twitterUrl": "https://twitter.com/starttsNSW",
      "facebookUrl": "https://www.facebook.com/STARTTSNSW",
      "instagramUrl": "https://www.instagram.com/startts_nsw/",
      "linkedinUrl": "https://www.linkedin.com/company/startts/",
      "youtubeUrl": "https://www.youtube.com/user/starttsvideos"
    },
    "county": "City of Fairfield",
    "title": "ताप आणि संताप वाऱ्यामुळे जी व्यक्ती जीवन जगते त्या व्यक्तींच्या उपचार व पुनर्वासाच्या सेवा करणारी NSW सर्विस",
    "description": "STARTTS ही एक विशेषत उपचार, नफा न घेणारी संस्था आहे जी सांस्कृतिक रीतीने मनोवैज्ञानिक उपचार, मदत, आणि समुदाय विदर्भ प्रस्तावित करते, त्यामुळे ताप आणि शरणार्थी संतापातून लोकांना आणि समुदायांना बरे होण्याची आणि ऑस्ट्रेलियात आपले आयुष्य सांगण्याची मदत करते. ते शरणार्थी आणि आश्रय शोधायला यायच्या पाठीशी असलेल्या LGBTQIA+ व्यक्तींसाठीही मदत करतात."
  },
  {
    "id": "18ba5d3d-c47d-47f8-90a4-2f353a1f13ce",
    "slug": "ftmguideorg",
    "externalUrl": "https://FTMGuide.org",
    "tags": [
      "non-binary",
      "transmasculine",
      "healthcare",
      "clothing"
    ],
    "title": "FTMGuide.org",
    "description": "स्त्रीते पुरुष (FTM) कडे स्थलांतर करणार्या व्यक्तींना समर्थन करण्यासमर्पित एक महत्त्वाचा ऑनलाइन प्लॅटफॉर्म. त्यांची वेबसाइट एक विश्वसनीय संसाधनम्हणून काम करते, मूलभूत माहिती, मार्गदर्शन आणि समुदायातील संबंधांसाठी एक समृद्ध संसाधन उपलब्ध करवुन देते. हार्मोन चिकित्सा आणि शस्त्रक्रिया पर्यायांवरील व्यवहारिक सल्ल्यासह मानसिक आरोग्य समर्थन आणि वैयक्तिक कथा, FTMGuide.org हे व्यक्तींना ज्ञान आणि संसाधने प्राप्त करण्याची क्षमता देऊन, त्यांच्या स्थलांतराच्या प्रवासाचे स्वतंत्रपणे आणि स्पष्टपणे नेविगेट करण्यास तयार करणारे."
  },
  {
    "id": "192cec64-3c1a-43eb-bfcf-9dfe3372842c",
    "slug": "black-rainbow",
    "externalUrl": "https://blackrainbow.org.au/",
    "tags": [
      "mental-health",
      "support-groups",
      "community-stories",
      "education-awareness"
    ],
    "address": "Darwin NT, Australia",
    "phoneNumber": null,
    "country": "AU",
    "provinceOrState": "NT",
    "city": "Darwin",
    "latLng": [
      -12.4637333,
      130.8444446
    ],
    "email": null,
    "socialMedia": {
      "instagram": "https://www.instagram.com/blackrainbowaus/",
      "twitter": "https://twitter.com/BlkRnBow",
      "facebook": "https://www.facebook.com/blackrainbowaus/",
      "linkedin": "https://www.linkedin.com/company/black-rainbow/",
      "youtube": "https://www.youtube.com/c/BlackRainbowAustralia"
    },
    "title": "ब्लॅक रेनबो",
    "description": "ब्लॅक रेनबो हे राष्ट्रीय अबॉरिजनी आणि टारेस स्ट्रैट आयलॅंडर LGBQTIA+SB स्वयंसेवी सामाजिक उद्योग आहे, ज्याचे आपल्या समुदायाच्या आरोग्य आणि कल्याणावर केंद्रीभूत आहे. हे त्याच्या सेवांचा विस्तार करण्याची कठीण प्रयत्न करते, जी मुद्रांकन नसलेली असताना, दान, सेवेची शुल्क आणि शैक्षणिक साहित्याची विक्रीद्वारे. ते आधारपात्री प्रकल्पांची सुरुवात करतात, सामाजिक कार्यक्रमांना समर्थन देतात आणि समुदाय सुधारणा आणि आरोग्य परिणामांवर संशोधन करण्यासाठी धन एकत्र करतात."
  },
  {
    "id": "19d3bf2d-04ed-46e6-ac5b-b2e3c26a7dd1",
    "slug": "minus-eighteen",
    "externalUrl": "https://www.minus18.org.au/",
    "tags": [
      "youth-services",
      "education-awareness"
    ],
    "address": null,
    "phoneNumber": null,
    "country": "AU",
    "provinceOrState": null,
    "city": null,
    "county": null,
    "latLng": null,
    "email": null,
    "socialMedia": null,
    "title": "Minus18",
    "description": "Minus18 ही ऑस्ट्रेलियाची लबाड मुद्दांसाठी काम करणारी संस्था आहे. त्यांनी या सामाजिक वेगळ्यातच्या युवांना त्यांची स्वतःची जगा और दोस्ती करण्याची जागा तयार करून ही समस्या सोडवण्याचा प्रयत्न केलेला आहे. त्यांनी LGBTQIA+ प्रशिक्षण, साधने, आणि डिजिटल अभियानांचा आयोजन केलेला आहे, असा ऑस्ट्रेलिया तयार करण्याची उद्दीश्त आहे ज्यामधे भेदभाव नसेल. त्यांच्या लक्ष्यात बदल घडविण्यासाठी आघाडीत असण्याच्या क्षमता आणि संधी मिळवून युवांना सुसज्ज करणे आहे."
  },
  {
    "id": "1d1d694e-b73a-4c37-ae8b-288fbc81a489",
    "slug": "us-trans-survey",
    "externalUrl": "https://www.ustranssurvey.org/",
    "tags": [
      "education-awareness",
      "community-stories",
      "non-binary",
      "transmasculine",
      "transfeminine"
    ],
    "address": null,
    "phoneNumber": null,
    "country": "US",
    "provinceOrState": null,
    "city": null,
    "county": null,
    "latLng": null,
    "email": "ustranssurvey@transequality.org",
    "socialMedia": null,
    "title": "यु.एस. ट्रान्स सर्वेक्षण",
    "description": "यु.एस. ट्रान्स सर्वेक्षण हे संयुक्त राज्यांमधील ट्रान्स लोकांच्या, ट्रान्स लोकांसाठी अगदी मोठे सर्वेक्षण आहे. त्यामध्ये 16 वर्षांपेक्षा जास्त वयाच्या ट्रान्स आणि नॉनबायनरी लोकांच्या अनुभवांची आणि जीवनाची दस्तावेजीकरण केली आहे. सर्वेक्षण आणि त्याच्या अहवालांमध्ये लोकांच्या अनुभवांच्या अहवालांचा समावेश असलेल्या अत्यंत महत्वाच्या संसाधनांपैकी एक आहे, ज्या मध्ये रंगबिरंगी लोकांच्या अनुभवांवर आणि राज्यानुसार अहवालांवर आधारित, ट्रान्सच्या आवाजाच्या माध्यमातून भविष्याच्या आकाराची योजना करण्यास मदत करते."
  },
  {
    "id": "1e8cb769-f49b-4428-86ea-2c4cbec96905",
    "slug": "transfemscienceorg",
    "externalUrl": "https://transfemscience.org",
    "tags": [
      "transfeminine",
      "non-binary",
      "healthcare"
    ],
    "title": "transfemscience.org",
    "description": "प्रमाणधारित संशोधन, शिक्षण आणि संचेतना प्रदान करणारा एक भूमिकेविध्या ऑनलाईन प्लॅटफॉर्म, विशेषतः स्त्रीत्वदायक हॉर्मोन चिकित्सा (FHT) वरती. त्यांचा वेबसाइट विश्वासू आणि अद्ययावत महत्त्वाच्या वैद्यकीय, शारीरिक, आणि मनोवैज्ञानिक पैलूंवर माहिती शोधत असलेल्या व्यक्तींसाठी महत्त्वाचे केंद्रस्थान ठरते. त्यांच्या सामग्रीसंग्रहातील केलेले पीर-समीक्षीत अध्ययन, तज्ज्ञ लेख, आणि व्यावहारिक मार्गदर्शक माध्यमातून, त्यांचा साइट व्यक्तींना त्यांच्या रुपांतराबधती आणि आरोग्याबधती माहितीपूर्ण निर्णय घेण्यास सामर्थ्य देतो."
  },
  {
    "id": "1ff064d4-6b1e-44e9-8b83-5e4e14d9f1ce",
    "slug": "nonbinary-ch-a-resource-for-non-binary-individuals",
    "externalUrl": "https://www.nonbinary.ch/",
    "tags": [
      "non-binary",
      "education-awareness"
    ],
    "address": null,
    "phoneNumber": null,
    "country": "CH",
    "provinceOrState": null,
    "city": null,
    "county": null,
    "latLng": null,
    "email": null,
    "socialMedia": {
      "yelpUrl": null,
      "googleMapsUrl": null,
      "youtubeUrl": "https://www.youtube.com/channel/",
      "pinterestUrl": "https://www.pinterest.com/nonbinarych/"
    },
    "title": "nonbinary.ch - नॉन-बायनरी व्यक्तींसाठीचे संसाधन",
    "description": "नॉन-बायनरी लिंग पोहच्या संबंधित माहिती आणि संसाधने प्रदान करणारी एक संपूर्ण स्विस वेबसाईट. हे त्यांच्या स्वत:च्या लिंग पोहच्याची शोध घेणार्या व्यक्तींना, किंवा नॉन-बायनरी व्यक्तींशी संपर्क साधत असलेल्या व्यक्तींना मूळभूत ज्ञान सहजपणे उपलब्ध करण्यासाठी मदत करते. साईटवर एक ब्लॉग, न्यूजलेटर आणि पुस्तके, चित्रपटे आणि संशोधनासारख्या संबंधित बाह्य संसाधनांच्या दुव्यांची मेजवाणीही आहे."
  },
  {
    "id": "2db72f6f-a5bc-4784-931d-dbe46b9657c6",
    "slug": "the-pinnacle-foundation",
    "externalUrl": "https://thepinnaclefoundation.org/",
    "tags": [
      "education-awareness",
      "financial-aid-scholarships",
      "youth-services"
    ],
    "address": null,
    "phoneNumber": null,
    "country": "AU",
    "provinceOrState": null,
    "city": null,
    "county": null,
    "latLng": null,
    "email": null,
    "socialMedia": null,
    "title": "द पिनेकल फाउंडेशन",
    "description": "द पिनेकल फाउंडेशन ही ऑस्ट्रेलियन शिक्षण दायित्व असलेली संस्था आहे जी तरुण LGBTQIA+ ऑस्ट्रेलियायनांना शिष्यवृत्त्या, मार्गदर्शन आणि संधी प्रदान करते. शिष्यवृत्त्या ऑस्ट्रेलियातील सार्वजनिक उच्च शिक्षण संस्थांवर पूर्णवेळी अभ्यासासाठी दिली जातात."
  },
  {
    "id": "2f23a24b-2e9d-4f83-9808-1e69981fba12",
    "slug": "ftm-portal-net",
    "externalUrl": "https://ftm-portal.net",
    "tags": [
      "transmasculine",
      "education-awareness",
      "support-groups"
    ],
    "address": null,
    "phoneNumber": null,
    "country": "DE",
    "provinceOrState": null,
    "city": null,
    "county": null,
    "latLng": null,
    "email": null,
    "socialMedia": null,
    "title": "FTM-Portal.net",
    "description": "FTM-Portal.net ही जर्मन भाषेतील सर्वात मोठी माहिती प्लॅटफॉर्म आहे ज्यामुळे ट्रांसमन आणि इतर ट्रान्समेसकुलिनिटीज्सला विविध जीवन स्थितींवरील अनुभव आणि सल्लेच्या मिळतात. हा संसाधन जे कोणतीही व्यक्ती ज्याला जन्मावेळी स्त्री असल्याचे केलेले वांधळलेले वर्गीकरण याशी पूर्णकिंवा अर्धवटता ओळखत नाही अशी असेल तिच्यासाठी उपयुक्त आहे. ट्रान्समन यांच्या नातेवाईकांनी आणि इतर सर्वांनी नोंदवडी करण्याची सुविधा असेल."
  },
  {
    "id": "2f6aa929-342d-4f12-a6a1-238cec4628ae",
    "slug": "tgns-transgender-network-switzerland",
    "externalUrl": "https://www.tgns.ch/",
    "tags": [
      "transmasculine",
      "non-binary",
      "transfeminine",
      "legal",
      "healthcare",
      "mental-health",
      "education-awareness",
      "youth-services",
      "support-groups",
      "parent-family-resources",
      "partner-resources"
    ],
    "address": null,
    "phoneNumber": null,
    "country": "CH",
    "provinceOrState": null,
    "city": null,
    "county": null,
    "latLng": null,
    "email": null,
    "socialMedia": {
      "facebookUrl": "https://www.facebook.com/transgenderch",
      "twitterUrl": "https://twitter.com/tgnsch",
      "instagramUrl": "https://www.instagram.com/tgns.ch/"
    },
    "title": "TGNS ट्रान्सजेंडर नेटवर्क स्वित्झर्लंड",
    "description": "TGNS ही स्वित्झर्लंडमधील ट्रान्सजेंडर व्यक्तींसाठीची नेटवर्क आहे. ते कायदेशीर समर्थन पुरवतात, आरोग्यसेवा सुधारण्याकडे काम करतात, आणि ट्रान्सजेंडर समुदायासाठी मानसिक आरोग्य संसाधने पुरवतात. त्यांची ही एक विविध जागरूकता आणि शिक्षण कार्यक्रमे असतात ज्यांच्या उद्दिष्टाने व्यक्तींच्या डोक्यात ट्रान्समॅस्क्युलिन, ट्रान्सफेमिनिन, व नॉन-बायनरी असलेल्या व्यक्तींसाठी सहाय्यक आणि समाविष्टानुकूल वातावरण तयार करण्याच्या प्रयत्नांत ते सक्रीय आहेत. TGNSमध्ये तरुण सेवा, सहाय्य गट, आणि ट्रान्सजेंडर व्यक्तींच्या कुटुंबीयांसाठीचे संसाधनही आहेत."
  },
  {
    "id": "3077e7a8-0764-4705-b4fd-95f63cf4f778",
    "slug": "medicijnkosten-medication-costs-information",
    "externalUrl": "https://www.medicijnkosten.nl/",
    "tags": [
      "healthcare",
      "financial-aid-scholarships"
    ],
    "address": null,
    "phoneNumber": null,
    "country": "NL",
    "provinceOrState": null,
    "city": null,
    "county": null,
    "latLng": null,
    "email": null,
    "socialMedia": null,
    "title": "मेडिसिनच्या खर्चांची माहिती - मेडिसिनच्या खर्चांची माहिती",
    "description": "एक माहितीपूर्ण प्लॅटफॉर्म ज्यामुळे औषधाच्या खर्चांबद्दलची तपशील मिळतात. त्यामध्ये औषधांच्या पूर्ततेविषयी डेटा देतो आणि व्यक्तींसाठी विकल्प देते ज्यांना काही औषधे मिळवता येऊ शकत नाहीत. आरोग्य क्षेत्रातील संधी योजनेच्या दृष्टीने महत्वाचे."
  },
  {
    "id": "313b4214-64cb-412e-a12e-06cf3ec67654",
    "slug": "open-doors-youth-service",
    "externalUrl": "https://www.opendoors.net.au/",
    "tags": [
      "mental-health",
      "social-services",
      "youth-services",
      "support-groups",
      "parent-family-resources",
      "education-awareness"
    ],
    "address": null,
    "phoneNumber": null,
    "country": "AU",
    "provinceOrState": "QLD",
    "city": null,
    "county": "South East Queensland",
    "latLng": null,
    "email": null,
    "socialMedia": {
      "instagramUrl": "https://www.instagram.com/opendoorsyouthservice/"
    },
    "title": "उघड्या दारवाजांची युवक सेवा",
    "description": "दक्षिण पूर्व क्वींसलँडमधील LGBTIQAP+ युवकांचे आणि त्यांच्या कुटुंबीयांचे समर्थन करणारे. मानसिक आरोग्य सल्लागारी, गट थेरपी कार्यक्रमे, सामाजिक संथ उपलब्ध करणारी सेवा, मूळभूत अन्न & स्वच्छता साहित्य पुरवठा करणे, स्थिर रोजगार आणि हाउसिंग सुरक्षित करणे, आणि शाळेत, कामगार संस्थेत आणि कुटुंबीयांसोबत प्रशिक्षण आणि शिक्षण कार्यक्रमे चालवणे."
  },
  {
    "id": "313cd7c6-1051-437c-a1d1-b1297f4c49a8",
    "slug": "stonewall-medical-centre-sexual-health-clinic-brisbane",
    "externalUrl": "https://www.stonewall.com.au/",
    "tags": [
      "healthcare",
      "HIV",
      "STI",
      "sex-workers",
      "transfeminine",
      "transmasculine",
      "non-binary"
    ],
    "address": "52 Newmarket Rd, Windsor QLD 4030, Australia",
    "phoneNumber": "07 3857 1222",
    "country": "AU",
    "provinceOrState": "QLD",
    "city": "Windsor",
    "county": "Brisbane",
    "latLng": [
      -27.4378562,
      153.0279458
    ],
    "email": null,
    "socialMedia": null,
    "title": "स्टोनवॉल वैद्यकीय केंद्र आणि लैंगिक आरोग्य क्लिनिक - ब्रिसबेन",
    "description": "स्टोनवॉल वैद्यकीय केंद्र १९९५ पासून ब्रिसबेनच्या लेस्बियन, समलिंगी, द्विलिंगी, लिंगभिन्न, लैंगिक समस्यांशी सामना करणाऱ्या (लेस्बियन, गे, बायसेक्स्युअल, ट्रान्सजेंडर, इंटरसेक्स आणि क्वीअर / प्रश्नित करणाऱ्या (LGBTQIA+), लैंगिक श्रमिकांच्या आणि सरळ / संस्थागत समुदायाचे सामान्य आरोग्य व लैंगिक आरोग्य अभिमानाने सेवा केले आहे. क्लिनिक HIV PEP आणि PrEP, STI चाचणी, लैंगिक कामगारांसाठी सल्लागारी, लिंगभिन्न आणि लिंग संकीर्ण व्यक्तींसाठी वैद्यकीय काळजी, स्टेरॉयड आणि प्रतिमा सुधारणारी औषधे नियंत्रण, आणि अन्यांच्या मध्ये संदर्भांची पुरवणूक करते."
  },
  {
    "id": "3143b616-c478-4c99-9cbd-ed16c89a1c70",
    "slug": "meridian-support",
    "externalUrl": "https://www.meridianact.org.au/",
    "tags": [
      "healthcare",
      "support-groups",
      "education-awareness",
      "community-stories"
    ],
    "address": "Havelock House, 85 Northbourne Ave, Turner ACT 2612, Australia",
    "phoneNumber": "(02) 6257 2855",
    "country": "AU",
    "provinceOrState": "ACT",
    "city": "Turner",
    "latLng": [
      -35.2736943,
      149.1291121
    ],
    "email": "contact@meridianact.org.au",
    "socialMedia": null,
    "title": "मेरिडियन",
    "description": "मेरिडियनने LGBTIQA+ समुदायासाठी प्रवाद आणि समर्थनासे 40 वर्षांसाठी केलेले आहे, कॅनबेरा प्रदेशात एचआईव्ही सेवा, कल्याण सेवा, लैंगिक कामगारांच्या आउटरीच कार्यक्रमांसह इतर सेवा आणि प्रक्रमांची सर्वांत मोठी श्रृंखला प्रदान करते."
  },
  {
    "id": "34974bb4-5b32-4157-8820-250bef7a47a8",
    "slug": "australian-transgender-support-association-of-queensland",
    "externalUrl": "https://www.atsaq.org.au/",
    "tags": [
      "non-binary",
      "support-groups",
      "community-stories",
      "social-services"
    ],
    "address": "Booval QLD 4304, Australia",
    "phoneNumber": "(07) 3705 7663",
    "country": "AU",
    "provinceOrState": "QLD",
    "city": "Booval",
    "county": "City of Ipswich",
    "latLng": [
      -27.614358,
      152.788861
    ],
    "email": "parker@atsaq.org.au",
    "socialMedia": null,
    "title": "ऑस्ट्रेलियन ट्रान्सजेंडर सपोर्ट असोसिएशन ऑफ क्वीन्सलैंड",
    "description": "1990 पासून क्वीन्सलैंडचे प्रमुख संघ ट्रान्सजेंडर, लिंग विविधता, आणि नॉन-बायनरी व्यक्तींचा प्रतिनिधित्व करणारे. त्यांनी ट्रान्सजेंडर समुदायास आधार, समर्थन, सेवा प्रदान केलेली आहेत आणि सामाजिक कार्यक्रमे व्यवस्थित केलेली आहेत."
  },
  {
    "id": "377cdcad-ac8e-491b-96aa-13a91886c07a",
    "slug": "jim-collins-foundation",
    "externalUrl": "https://jimcollinsfoundation.org/",
    "tags": [
      "healthcare",
      "financial-aid-scholarships"
    ],
    "address": "New York, NY 10150, USA",
    "phoneNumber": null,
    "country": "US",
    "provinceOrState": "NY",
    "city": "New York",
    "county": "New York County",
    "latLng": [
      40.7582228,
      -73.9704871
    ],
    "email": null,
    "socialMedia": null,
    "town": "Manhattan",
    "title": "जिम कॉलिन्स फाउंडेशन",
    "description": "जिम कॉलिन्स फाउंडेशन (JCF) चे उद्दीष्ट असलेल्या व्यक्तींना लिंग-प्रतिपादन सर्जरीसाठी आर्थिक मदत करणे आहे. ही फाउंडेशन दोन अनुदान पर्यायंची प्रस्तावना करते; संस्थापकांची अनुदान ज्याच्या मदतीने शल्यक्रियेच्या खर्चा 100% कवर केलेला असतात व ‘क्रिसालिस अन्न हेम्ब्रो वारसा कोष’ ज्याच्या मदतीने शस्त्रक्रियेच्या खर्चांची 50% कवर केलेली असते. फाउंडेशन च्या उद्दीष्टां पैकी एक म्हणजे या महत्वाच्या शस्त्रक्रिया सुलभ तरीते मिळवू आणि ज्यांनी ती इच्छित असेल, असे करण्यासाठी प्रयत्न करण्याचा आहे. प्रांतता येथे लिंगभेद केलेल्या व्यक्तींच्या विरोधात असलेल्या भेदभावामुळेच अस्थंपतित खर्च किंवा सामान्यता कबूल करणे किंवा सक्षमता प्राप्त करणे सामान्यत: अशक्य असतात."
  },
  {
    "id": "397b0b03-c59f-46aa-93aa-14170895e5dd",
    "slug": "transgender-india-transition-guide",
    "externalUrl": "https://transgenderindia.com/",
    "tags": [
      "legal",
      "healthcare",
      "mental-health",
      "education-awareness"
    ],
    "address": null,
    "phoneNumber": null,
    "country": "IN",
    "provinceOrState": null,
    "city": null,
    "county": null,
    "latLng": null,
    "email": "enquiry@transgenderindia.com",
    "socialMedia": null,
    "title": "संवेदनशील भारत: तुमची स्थलांतर गाईड",
    "description": "संवेदनशील भारत म्हणजे भारतीय संवेदनशील समुदायांसाठी विस्तृत अभ्यासक्रमे, लेख आणि संसाधने प्रदान करते. हे हॉर्मोन प्रतिस्थापन उपचाराच्या मूलभूतांपासून, कायदी हक्क आणि संरक्षण, सामाजिक स्थलांतरणांपर्यंतचे विषय आहेत, ज्या विविध क्षेत्रांतील तज्ज्ञांनी अभ्यासक्रमे नेमलेली आहेत."
  },
  {
    "id": "3a95da73-255a-41db-a65c-233c1f236c3b",
    "slug": "queermed-deutschland-directory",
    "externalUrl": "https://queermed-deutschland.de/",
    "tags": [
      "healthcare",
      "transmasculine",
      "non-binary",
      "transfeminine"
    ],
    "address": null,
    "phoneNumber": null,
    "country": "DE",
    "provinceOrState": null,
    "city": null,
    "county": null,
    "latLng": null,
    "email": null,
    "socialMedia": {
      "twitterUrl": "https://twitter.com/queermeddeutschland",
      "instagramUrl": "https://instagram.com/queermeddeutschland",
      "linkedinUrl": "https://linkedin.com/company/queermeddeutschland",
      "facebookUrl": "https://facebook.com/queermeddeutschland"
    },
    "title": "Queermed जर्मनी निर्देशिका",
    "description": "Queermed जर्मनी म्हणजे एलजीबीटीक्यूआयए+ समुदायाने शिफारसी केलेल्या डॉक्टरांची, थेरपिस्टांची आणि प्रॅक्टिस्सची निर्देशिका, जर्मनीमध्ये. आरोग्यव्यवस्थेतील भेदभाव विरुद्ध संघर्ष करण्याचे हेतू आहे, सर्वांसाठी सन्मानजनक आणि संवेदनशील आरोग्यसेवा खात्री करणे. त्यामध्ये समुदायाच्या विविधांसाठी अज्ञात प्रश्नावलीतील विविधतम विकल्प असतात."
  },
  {
    "id": "3b112584-39e6-4ef6-9e75-a465acdea54c",
    "slug": "northern-territory-aids-and-hepatitis-council-inc",
    "externalUrl": "https://www.ntahc.org.au/",
    "tags": [
      "healthcare",
      "social-services",
      "education-awareness"
    ],
    "address": "46 Woods St, Darwin City NT 0800, Australia",
    "phoneNumber": "08 8944 7777",
    "country": "AU",
    "provinceOrState": "NT",
    "city": "Darwin City",
    "county": "City of Darwin",
    "latLng": [
      -12.4602736,
      130.8432107
    ],
    "email": "info@ntahc.org.au",
    "socialMedia": {
      "yelpUrl": null,
      "googleMapsUrl": "https://www.google.com/maps?q=46+Woods+StreetDARWIN+NT+0800"
    },
    "title": "नॉर्दर्न टेरिटरी एड्स अँड हेपेटायटीस कॉउन्सिल इन्क.",
    "description": "नॉर्दर्न टेरिटरी मधील रक्त प्राप्त विषाणूंच्या प्रतिसादाचे समुदाय. त्यांच्या संचाराचा निर्मूलन करण्याची ध्येयी धंवनी देत आहे. एलजीबीटीआय जगण्यास मदत करणारी, लैंगिक कामगारी प्रसार कार्य, आरोग्य प्रमोशन आणि आरोग्य क्लिनिक प्रदान करणारी सेवा देते."
  },
  {
    "id": "3b5a33bd-aba4-4205-9a86-293b172e38ee",
    "slug": "genderdysphoriafyi",
    "externalUrl": "https://genderdysphoria.fyi",
    "tags": [
      "transmasculine",
      "non-binary",
      "transfeminine",
      "mental-health",
      "support-groups",
      "community-stories",
      "education-awareness"
    ],
    "title": "genderdysphoria.fyi",
    "description": "लिंग असंतृप्तीबद्दल माहिती, समर्थन आणि समजूतदारी शोधणाऱ्या व्यक्तींसाठी एक विश्वसनीय ऑनलाईन संसाधन. त्यांची वेबसाइट माहिती, संसाधने आणि समुदाय संबंध यांची समृद्धता पुरविते एवढी की व्यक्तींच्या प्रवासावर त्यांचे सामर्थ्य वाढवण्याची त्यांच्याकडे क्षमता असते. लिंग पहचान आणि संकल्पनेवरील व्यापक मार्गदर्शक पासून स्वत:च्या संगणकांपर्यंत आणि तज्ज्ञांच्या सल्ल्यांपर्यंत, ते सर्वांसाठी सुरक्षित आणि समावेशक स्थान तयार करण्याचा प्रयत्न करतात."
  },
  {
    "id": "3f865b77-21e6-472e-be98-b2cfd999dafb",
    "slug": "unitarian-universalist-association",
    "externalUrl": "https://www.uua.org/",
    "tags": [
      "non-binary",
      "support-groups",
      "education-awareness",
      "spiritual"
    ],
    "address": "24 Farnsworth St, Boston, MA 02210, USA",
    "phoneNumber": "(617) 742-2100",
    "country": "US",
    "provinceOrState": "MA",
    "city": "Boston",
    "county": "Suffolk County",
    "latLng": [
      42.35163259999999,
      -71.04857050000001
    ],
    "email": "info@uua.org",
    "socialMedia": null,
    "title": "युनिटेरियन यूनिवर्सलिस्ट संघ",
    "description": "न्याय, प्रेम, ग्रंथपठन आणि आशा च्या जीवनाला समर्थन देणारी खुलेआत्मक, हृदयाची खुली असलेली आध्यात्मिक समुदाय. ह्या समुदायात विविधतेच्या सहाव्याचा स्वागत केला जातो, समावेशी तरुण यांचा समावेश असा समावेशी. त्यांनी विविध सामाजिक समस्यांसाठी संसाधने, मदत आणि समर्थन दिलेले आहे."
  },
  {
    "id": "4332f79d-1323-45ca-9b40-df63af9b7179",
    "slug": "movement-advancement-project",
    "externalUrl": "https://www.lgbtmap.org/",
    "tags": [
      "legal",
      "healthcare",
      "education-awareness"
    ],
    "address": "1905 15th St #1097, Boulder, CO 80302, USA",
    "email": null,
    "phoneNumber": "(303) 578-4600",
    "country": "US",
    "provinceOrState": "CO",
    "city": "Boulder",
    "county": "Boulder County",
    "latLng": [
      40.0178641,
      -105.2763041
    ],
    "socialMedia": {
      "yelpUrl": null,
      "googleMapsUrl": null,
      "facebookUrl": "https://www.facebook.com/lgbtmap/",
      "twitterUrl": "https://twitter.com/lgbtmap",
      "instagramUrl": "https://www.instagram.com/lgbtmap/",
      "youtubeUrl": null,
      "tiktokUrl": null,
      "twitchUrl": null,
      "patreonUrl": null
    },
    "title": "संचालन प्रगती प्रकल्प",
    "description": "संचालन प्रगती प्रकल्प (MAP) हे एक स्वतंत्र, गैरनफायदेशीर विचारगृह आहे जित्र कडून गंभीर संशोधन, अंतर्दृष्टी, आणि संवाद सर्वांसाठी समानता आणि संधी वेगवेगळ्या गतीने उपलब्ध होणार्या मदतीसाठी प्रदान केलेल्या जाऊन दिलेल्या आहेत. MAP यांनी काही कार्य केलेले आहे तरी की सर्व लोकांना आरोग्य आणि सुख, जीवनोपयोगी व्यवसाय करण्याचा, त्यांच्या प्रेयसींची काळजी घेण्याचा, त्यांच्या समुदायात सुरक्षित राहण्याचा, आणि नागरिक जीवनात सहभागी व्हाण्याचा न्यायसंगत अवसर आहे, याची खात्री केली आहे."
  },
  {
    "id": "43609b17-7528-4c60-94b4-e90866144715",
    "slug": "jordan-ross-communication-services",
    "externalUrl": "https://www.jordanrosscommunication.com/",
    "tags": [
      "voice-training"
    ],
    "socialMedia": {
      "yelpUrl": null,
      "googleMapsUrl": null,
      "facebookUrl": null,
      "twitterUrl": null,
      "instagramUrl": "https://www.instagram.com/jordanrosscommunication/",
      "youtubeUrl": "https://www.youtube.com/channel/UC4o7h219hPYdBcPaFpgh9Yw",
      "tiktokUrl": "https://www.tiktok.com/@jordanrosscommunication",
      "twitchUrl": null,
      "patreonUrl": null
    },
    "title": "जॉर्डन रॉस संवाद सेवा",
    "description": "जॉर्डन रॉस, त्रांस, क्विअर आणि लिंग अनुपालन न करणार्‍या व्यक्तींसाठी वाग्य, स्वर आणि संवाद कोचिंग प्रदान करतात. त्याने 1-वन- 1 कोचिंग, ऑनलाइन अभ्यासक्रम, इव्हेंट सह व 'वॉयस विदिन कोचिंग प्रोग्राम' प्रदान केला आहे. त्याच्या अभिगमामध्ये न्युरो-लिंग्विस्टिक प्रोग्रामिंग, हायप्नोथेरपी, योग शिक्षण, आणि श्वसन कोचिंग समाविष्ट आहे, ज्याचे ध्यास फक्त भौतिक पर्यायी, परंतु मानसिक, भावनात्मक, आणि ऊर्जासंबंधी संवादाच्या पैलूंवरही ठेवलेले आहे."
  },
  {
    "id": "4465cbb7-3513-41ae-8878-7a86ebbe9f6a",
    "slug": "gender-dynamix-online-education-portal",
    "externalUrl": "https://www.genderdynamix.org.za/",
    "tags": [
      "transfeminine",
      "transmasculine",
      "non-binary",
      "legal",
      "healthcare",
      "education-awareness",
      "support-groups",
      "community-stories"
    ],
    "address": "7, 10 Anson St, Observatory, Cape Town, 7925, South Africa",
    "phoneNumber": "+27 (0)21 447 4797",
    "country": "ZA",
    "provinceOrState": "WC",
    "city": "Cape Town",
    "county": "City of Cape Town Metropolitan Municipality",
    "latLng": [
      -33.9368811,
      18.470378
    ],
    "email": "info@genderdynamix.org.za",
    "socialMedia": null,
    "town": "Observatory",
    "title": "जेंडर डायनेमिक्स ऑनलाईन शिक्षण पोर्टल",
    "description": "जेंडर डायनेमिक्स हे एक आफ्रिकेतील गैर-नफादारी संस्था आहे जी दक्षिण आफ्रिका आणि दक्षिणी आफ्रिकेतील ट्रांस आणि लिंगानुसार वेगळ्या समुदायांच्या मानवी हक्कांचे संवर्धन, प्रोत्साहन आणि संरक्षण करण्याचा ध्यास ठेवते. संस्था प्रतिनिधीत्व करते, क्षमतावर्धन सुविधा पुरवते आणि समुदायास सीधी सेवा पुरवते. त्यांनी आरोग्यसेवा, शैक्षणिक कार्यक्रम, आणि कायदेशीर लिंग पहचान संबंधित ऑनलाईन संसाधने देत आहेत."
  },
  {
    "id": "47b17f76-670a-4835-8773-409d98934b91",
    "slug": "sylvia-rivera-law-project",
    "externalUrl": "https://srlp.org/",
    "tags": [
      "transmasculine",
      "non-binary",
      "transfeminine",
      "legal",
      "healthcare",
      "mental-health",
      "social-services",
      "community-stories",
      "education-awareness"
    ],
    "address": "147 W 24th St #5th, New York, NY 10011, USA",
    "phoneNumber": "212-337-8550",
    "country": "US",
    "provinceOrState": "NY",
    "city": "New York",
    "town": "Manhattan",
    "county": "New York County",
    "latLng": [
      40.744576,
      -73.9941166
    ],
    "socialMedia": {
      "yelpUrl": "https://www.yelp.com/biz/sylvia-rivera-law-project-new-york?osq=sylvia+rivera+law+project",
      "googleMapsUrl": "https://goo.gl/maps/sjGv8qoSZPe3XE2QA",
      "facebookUrl": "https://www.facebook.com/sylviariveralawproject",
      "twitterUrl": "https://www.twitter.com/srlp",
      "instagramUrl": "https://instagram.com/sylviariveralawproject/",
      "youtubeUrl": "https://www.youtube.com/user/SylviaRiveraLP",
      "tiktokUrl": null,
      "twitchUrl": null,
      "patreonUrl": null
    },
    "title": "सिल्विया रिवेरा विधी प्रकल्प (SRLP)",
    "description": "सिल्विया रिवेरा विधी प्रकल्प असा काम करतो की सर्व लोक मुग उत्पन्न केलेल्या लिंग ओळख व व्यक्तीमत्व, उद्योग किंवा जातीच्या परवानगीशिवाय, त्रास, भेदभाव किंवा हिंसा त्यांना सामोरे करण्याची चूक न करता, धरली जाईल. SRLP विधी सहाय्य प्रदान करते, अभियानांची संचालन करते, प्रशिक्षणे घेतली जातात, व सोडतीच्या सल्लागार समितीचे कार्य करते. समुदायातील सहभाग सहयोगाच्या रुपात, स्वयंसेवामध्ये, व सदस्यतेमध्ये प्रोत्साहित केले जाते."
  },
  {
    "id": "499aa5dd-d3c0-42f6-a686-853672f3c71e",
    "slug": "erin-in-the-morning",
    "externalUrl": "https://www.erininthemorning.com/",
    "tags": [
      "transfeminine",
      "legal",
      "healthcare",
      "education-awareness"
    ],
    "email": "null",
    "socialMedia": {
      "facebook": "facebook.com/erininthemorning",
      "email": "mailto:info@erininthemorning.com"
    },
    "title": "सकाळी एरिन",
    "description": "प्रतिसत्ता विधानावरील बातमी आणि चर्चा आणि जीवन. एरिन रीड द्वारे · 38,000 पेक्षा अधिक सदस्य"
  },
  {
    "id": "4a930816-9948-45d7-9513-393087685a01",
    "slug": "trans-health-sa",
    "externalUrl": "https://www.transhealthsa.com/",
    "tags": [
      "healthcare",
      "legal",
      "social-services",
      "support-groups",
      "education-awareness"
    ],
    "address": null,
    "phoneNumber": null,
    "country": "AU",
    "provinceOrState": "SA",
    "city": null,
    "county": null,
    "latLng": null,
    "email": null,
    "socialMedia": {
      "facebookUrl": "https://www.facebook.com/TransHealthSA",
      "googleMapsUrl": null,
      "yelpUrl": null
    },
    "title": "Trans Health SA",
    "description": "Trans Health SA ही एक स्वयंसेवी संघटना आहे जी दक्षिण ऑस्ट्रेलियातील ट्रान्स आणि लिंग-विविध लोकांच्या आरोग्याच्या गरजांसाठी माहिती आणि मदत प्रदान करण्यासाठी अस्तित्वात आहे. ती सन्मानशील प्रविद्यांच्या याद्या, वैद्यकीय आणि कायदेशीर माहिती, सहाय्यक संस्थांची माहिती, संगठने, प्रकाशने, सामाजिक आणि समर्थन समूह आणि ट्रान्सजेंडर समुदायाने तयार केलेले साधने प्रदान करते."
  },
  {
    "id": "4be75e80-8ce1-4f46-90f0-ad307cd1829b",
    "slug": "equaldexcom",
    "externalUrl": "https://EqualDex.com",
    "tags": [
      "transfeminine",
      "non-binary",
      "transmasculine",
      "partner-resources"
    ],
    "title": "EqualDex.com",
    "description": "एक अभिप्रेती ऑनलाईन प्लॅटफॉर्म ज्याचा लक्ष महाराष्ट्रातील एलजीबीटीक्यू+ अधिकारांची समग्र आणि वर्तमान स्तरावरील स्थळी तयार करण्यास आहे. त्यांची वेबसाईट जगभरातील एलजीबीटीक्यू+ अधिकारांवरील मतांच्या, नीत्यांच्या आणि समाजाच्या दृष्टिकोनाच्या अधिसूचनांची संकेन्द्रित डेटाबेस प्रदान करते. समानता, सम्वेशीत्व आणि कायदेशीर विरोधाभासावरील डेटाच्या मानचित्रणाच्या आणि दृश्यविलासनाद्वारे, EqualDex.com म्हणजेच वावर्तोमागणार्‍या, संशोधकांच्या आणि जगातील एलजीबीटीक्यू+ अधिकारांच्या अभिप्रेती वैयतिगतांसाठी एक प्रबळ साधन उपलब्ध करते. त्यांच्या इंटरॅक्टिव मानचित्रे अन्वेषण करा, देशविशिष्ट प्रोफाइल्स ब्राउज करा, आणि जगातभरातील एलजीबीटीक्यू+ समुदायाच्या समोर येणाऱ्या नवनवीन प्रगती आणि आव्हानांबद्दल माहितीपूर्ण राहा."
  },
  {
    "id": "539168d5-49aa-492c-bfb0-d0a1d9bba1eb",
    "slug": "gender-affirmative-letter-access-project",
    "externalUrl": "https://thegalap.org/",
    "tags": [
      "healthcare",
      "mental-health"
    ],
    "address": null,
    "phoneNumber": null,
    "country": null,
    "provinceOrState": null,
    "city": null,
    "county": null,
    "latLng": null,
    "email": null,
    "socialMedia": null,
    "title": "लिंग संबंधीत पत्र प्रवेश प्रकल्प",
    "description": "जी.ए.एल.ए.पी. हे लिंगांनुसार स्वीकार मिळवणार्‍या स्वतंत्र उपचारकांसाठी एक प्लॅटफॉर्म आहे. ते उपचारक सूची, लिंग पुष्टीसाठी पत्र लेखन मार्गदर्शक इत्यादी साधनांची सुविधा पुरवतात. कृपया लक्षात ठेवा, कोणत्याही प्रतिज्ञापत्राच्या सहीकरणाची कुशलता किंवा तज्ञता जीएएलएपीने पडताळणी करता येत नाही."
  },
  {
    "id": "581b9bb9-0e33-4887-8bf0-0dda3781202c",
    "slug": "a-gender-agenda",
    "externalUrl": "https://genderrights.org.au/",
    "tags": [
      "transmasculine",
      "non-binary",
      "transfeminine",
      "legal",
      "healthcare",
      "mental-health",
      "social-services",
      "youth-services",
      "support-groups",
      "parent-family-resources",
      "partner-resources",
      "community-stories",
      "education-awareness",
      "financial-aid-scholarships"
    ],
    "address": null,
    "phoneNumber": "(02) 6162 1924",
    "country": "AU",
    "provinceOrState": null,
    "city": "Canberra",
    "county": null,
    "latLng": null,
    "email": null,
    "socialMedia": null,
    "title": "एक लिंग विषयक्रम",
    "description": "एक लिंग विषयक्रम इंटरसेक्स, ट्रांस आणि लिंग विविध लोकांसह व त्यांच्या मित्र, कुटुंबीयांच्या कडे, आणि मित्रांच्या कडे कार्य करतो. शिक्षण, समर्थन, समुत्साहित मित्रांच्या समर्थनाद्वारे, आणि व्यावसायिक संगठनांद्वारे, AGA लोकांना एकमेकांशी जोडतो आणि सामूहिक अनुभवांवर आधारित असतो. त्यांनी समुदायासाठी अनेक कार्यक्रमांची आणि संसाधनांची सोय दिली आहे, समर्थन समूह, प्रशिक्षण, शैक्षणिक संसाधने सह. त्यांनी समर्थन आणि संकट हेल्पलाईन प्रदान केली आहे."
  },
  {
    "id": "58738396-e4d7-424a-ba8d-59559e883f06",
    "slug": "strandsfortransorg",
    "externalUrl": "https://strandsfortrans.org",
    "tags": [
      "transfeminine",
      "non-binary",
      "transmasculine",
      "friendly-businesses",
      "makeup"
    ],
    "title": "strandsfortrans.org",
    "description": "Strands For Trans हे सर्वांसाठी, विशेषतः ट्रान्स समुदायातील अतिथींसाठी सुरक्षित व पॉझिटिव अनुभव निर्माण करण्याच्या धोरणीला प्रेरणा देणार्या केस, सौंदर्य आणि आरोग्य उद्योगांची व अभिघातांची जागतिक संकेतस्थळ आहे."
  },
  {
    "id": "594ba858-974c-4c09-8fd4-f4bb35ca6c5f",
    "slug": "pacific-center-for-human-growth",
    "externalUrl": "https://www.pacificcenter.org/",
    "tags": [
      "mental-health",
      "support-groups",
      "healthcare",
      "youth-services",
      "education-awareness"
    ],
    "address": "2712 Telegraph Ave, Berkeley, CA 94705, USA",
    "phoneNumber": "510-548-8283",
    "country": "US",
    "provinceOrState": "CA",
    "city": "Berkeley",
    "county": "Alameda County",
    "latLng": [
      37.8611143,
      -122.2593404
    ],
    "socialMedia": {
      "yelpUrl": "https://www.yelp.com/biz/pacific-center-berkeley",
      "googleMapsUrl": "https://goo.gl/maps/dSnoipA7TWiDN72b7",
      "facebookUrl": "https://www.facebook.com/pacific.center",
      "twitterUrl": null,
      "instagramUrl": "https://www.instagram.com/pacificcenterberkeley/",
      "youtubeUrl": "https://www.youtube.com/user/TheInQueery",
      "tiktokUrl": null,
      "twitchUrl": null,
      "patreonUrl": null
    },
    "title": "पॅसिफिक सेंटर फॉर ह्युमन ग्रोथ",
    "description": "1973 मध्ये स्थापित झालेल्या, पॅसिफिक सेंटर फॉर ह्युमन ग्रोथ ही बे एरियातील सर्वात जुनी LGBTQIA+ केंद्र आहे, देशातील तिसरी सर्वात जुनी आणि अलामेदा काउंटीतील LGBTQIA+ व् QTBIPOC लोकांसाठी आणि त्यांच्या कुटुंबियांसाठी फक्त स्लाइडिंग स्केल मानसिक आरोग्य क्लिनिक चालवते."
  },
  {
    "id": "5ac3fd1a-2d29-4001-b51c-d3b62d81e090",
    "slug": "transgender-victoria",
    "externalUrl": "https://tgv.org.au/",
    "tags": [
      "transmasculine",
      "transfeminine",
      "non-binary",
      "legal",
      "healthcare",
      "mental-health",
      "social-services",
      "support-groups",
      "parent-family-resources",
      "partner-resources",
      "education-awareness"
    ],
    "address": null,
    "phoneNumber": null,
    "country": "AU",
    "provinceOrState": "VIC",
    "city": null,
    "county": null,
    "latLng": null,
    "email": null,
    "socialMedia": {
      "facebookUrl": "https://www.facebook.com/TransGenderVictoria/",
      "twitterUrl": "https://twitter.com/transgendervic",
      "instagramUrl": "https://www.instagram.com/transgendervic/"
    },
    "title": "ट्रान्सजेंडर व्हिक्टोरिया",
    "description": "TGV हे ट्रान्स आणि लिंग विविधतेच्या लोकांसाठी व्हिक्टोरियाचे मुख्य संघ आहे. आम्ही आपल्या समुदायांसाठी न्याय, समानता आणि सहभागीता साध्य करण्यासाठी काम करतो, त्याचे भागीदार, कुटुंब, मित्र, आणि मित्र. आम्ही वेगवेगळ्या संसाधने, प्रशिक्षण, म्हणजेच, समाजिक, आर्थिक, आरोग्य, कल्याण, आणि ट्रान्सजेंडर समुदायाच्या मानसिक आरोग्य परिणामांसाठी समर्थन सेवा प्रदान करतो."
  },
  {
    "id": "682fba48-f668-4fe6-89a7-05a90193e778",
    "slug": "oakland-lgbtq-community-center",
    "externalUrl": "https://www.oaklandlgbtqcenter.org/",
    "tags": [
      "transmasculine",
      "non-binary",
      "transfeminine",
      "legal",
      "healthcare",
      "mental-health",
      "social-services",
      "youth-services",
      "support-groups",
      "parent-family-resources",
      "education-awareness",
      "financial-aid-scholarships",
      "community-stories",
      "partner-resources"
    ],
    "address": "3207 Lakeshore Ave, Oakland, CA 94610, USA",
    "phoneNumber": "510-882-2286",
    "country": "US",
    "provinceOrState": "CA",
    "city": "Oakland",
    "county": "Alameda County",
    "latLng": [
      37.8103802,
      -122.2459822
    ],
    "socialMedia": {
      "yelpUrl": null,
      "googleMapsUrl": "https://goo.gl/maps/EnhwARKBin25SAmA6",
      "facebookUrl": "https://www.facebook.com/oaklandlgbtqcommunitycenter/?notify_field=blurb&modal=profile_completion&notif_t=page_profile_blurb&notif_id=1499829595947085",
      "twitterUrl": null,
      "instagramUrl": "https://www.instagram.com/oaklandlgbtqcenter",
      "youtubeUrl": "https://youtu.be/3qxj1a9esuU",
      "tiktokUrl": null,
      "twitchUrl": null,
      "patreonUrl": null
    },
    "title": "ओकलॅंड LGBTQ समुदाय केंद्र",
    "description": "ओकलॅंडचे एकच निधी विनियोग 501c3, सर्व वयोगटां, सर्व समाविष्ट LGBTQ समुदाय सेवा केंद्र. सेवेमध्ये समर्थन समूह, मानसिक आरोग्य समर्थन, निवास सहाय्य, तरुण कार्यक्रम, कायद्याशास्त्रीय चौकशी, अन्नकोठर इत्यादी समाविष्ट आहे. वयस्क LGBTQ+ लोक आणि तरुणसमुदाय सदस्यांसाठी विशेष कार्यक्रमही केलेले आहे."
  },
  {
    "id": "6b4856a7-8cc7-4935-b5ee-bd6ca0dd9a4c",
    "slug": "plume-transgender-nonbinary-healthcare",
    "externalUrl": "https://getplume.co/",
    "tags": [
      "transmasculine",
      "non-binary",
      "transfeminine",
      "healthcare",
      "support-groups"
    ],
    "address": null,
    "phoneNumber": null,
    "country": null,
    "provinceOrState": null,
    "city": null,
    "county": null,
    "latLng": null,
    "email": null,
    "socialMedia": {
      "twitter": "https://twitter.com/getplume",
      "instagram": "https://www.instagram.com/getplume/",
      "youtube": "https://www.youtube.com/channel/UC_n1AJ_PeVNSPt14kjmSeTw",
      "linkedin": "https://www.linkedin.com/company/plume-healthcare",
      "tiktok": "https://www.tiktok.com/@get.plume"
    },
    "title": "Plume",
    "description": "ट्रान्स आणि नॉनबायनरी समुदायासाठी सर्वात मोठा आरोग्य सेवा प्रदाता, ज्यामध्ये लिंग पुष्टी हॉर्मोन चिकित्सा आणि संक्रमण सहाय्यासह चिंता आणि उदासीनता साठीच्या औषधांची विविध सेवा दिली जाते. ट्रान्स-वयस्कांच्या एक टीमने सेवा प्रदान केली आहे, ज्यामध्ये समुदायाच्या अद्वितीय आरोग्यसेवा आवश्यकतांची सामग्री समजली आहे, ज्याच्या उद्दीष्टाने तुम्हाला सुखकर, दृष्टीघेतली आणि देखील केली जाऊ शके. तुम्ही तुमची मूळ स्वतःम्हणून असू शकता आणि तुम्हाला आवश्यक असलेली काळजी घ्यायला एक ठिकाण."
  },
  {
    "id": "6bf639a8-0301-4061-80c2-7738672b036f",
    "slug": "trans-in-3-steps",
    "externalUrl": "https://johanna4711.github.io/Trans-in-3-Schritten/",
    "tags": [
      "transmasculine",
      "non-binary",
      "transfeminine",
      "legal",
      "healthcare",
      "mental-health",
      "education-awareness",
      "voice-training"
    ],
    "address": null,
    "phoneNumber": null,
    "country": "DE",
    "provinceOrState": null,
    "city": null,
    "county": null,
    "latLng": null,
    "email": "johanna4711@zohomail.eu",
    "socialMedia": {
      "githubUrl": "https://github.com/johanna4711/Trans-in-3-Schritten"
    },
    "title": "त्रान्स*मधील 3 पायरी",
    "description": "या प्रकल्पाचा मुख्य उद्दिष्ट एका व्यक्तीच्या परिवर्तनादरम्यान मदत करणारा मार्गदर्शक म्हणून काम करणे आहे. यात त्रान्स*संबंधी शब्दसंग्रह, त्रान्स*असल्याची कशी ओळख मिळवायची माहिती, मनोवैज्ञानिक सल्लागारीसाठी संसाधने, वैद्यकीय प्रक्रिया, मुखेदर्शक कथांमधील आपल्या किंवा मुलीच्या किंवा मुलांच्या लिंग परिवर्तनाच्या कथा, नाव आणि लिंग स्थिती बदलण्यासाठीची कायदेशीर माहिती आणि विविध संसाधने आणि सेवांच्या लिंकसह असलेली माहिती समाविष्ट केली आहे."
  },
  {
    "id": "6f38810d-896c-4493-afe2-b612021122fc",
    "slug": "the-shed-melbourne",
    "externalUrl": "https://www.theshedsupport.org.au/",
    "tags": [
      "transmasculine",
      "mental-health",
      "support-groups",
      "healthcare",
      "social-services"
    ],
    "address": "412 Lygon St, Brunswick East VIC 3057, Australia",
    "phoneNumber": null,
    "country": "AU",
    "provinceOrState": "VIC",
    "city": "Brunswick East",
    "county": "City of Merri-bek",
    "latLng": [
      -37.76497579999999,
      144.9730678
    ],
    "email": null,
    "socialMedia": null,
    "title": "द शेड मेलबोर्न",
    "description": "ट्रान्समास्कुलिन व्यक्तींसाठी मेलबोर्नस्थ आधारित समर्थन गट, पीर समर्थन बैठकीं, जिम क्लब, पुस्तक क्लब, मानसिक आरोग्य स्त्रोत, शल्यक्रिया आणि टेस्टोस्टेरोन माहिती आणि समर्थन, बिंदर कार्यक्रमे, आणि अधिक असे विविध कार्यक्रमे आणि स्त्रोत प्रदान करतो."
  },
  {
    "id": "7510c3ea-47b1-4a60-bfaf-bb98b6f6b5b2",
    "slug": "mapping-attacks-on-lgbtq-rights-in-u.s.-state-legislatures",
    "externalUrl": "https://www.aclu.org/legislative-attacks-on-lgbtq-rights",
    "tags": [
      "legal"
    ],
    "address": null,
    "phoneNumber": null,
    "country": "US",
    "provinceOrState": null,
    "city": null,
    "county": null,
    "latLng": null,
    "email": null,
    "socialMedia": null,
    "title": "संयुक्त राज्य राज्य संघटनेमधील LGBTQ अधिकारांवरील हल्ल्याचा मानचित्रण",
    "description": "शेवटच्या काही वर्षांमध्ये राज्ये LGBTQ अधिकारांच्या, विशेषतः किन्नर किशोरांवर हल्ला करणारी हिशोबी बिले प्रगत केलेली आहेत. ACLU ह्या हल्ल्यांचा पाहणाऱ्या आणि आमच्या राष्ट्रीय संघटनेतील गणांच्या मदतीसाठी काम करीत आहेत. अजून अनेक राज्ये प्रत्येक वर्षी LGBTQ लोकांना संरक्षण देणारी कायदे पास करण्याच्या प्रयत्नात आहेत, परंतु राज्य संघटना किन्नर लोकांच्या उद्दीष्टाने बिले प्रगत करीत आहेत, स्थानिक संरक्षणे मर्यादित करीत आहेत आणि भेदभाव करण्यासाठी धर्माचा वापर परवानगी देणारी आहेत. ACLU ही क्रूर हल्ल्यांविरुद्ध राष्ट्रव्यापीत बोलणार थांबणार नाही."
  },
  {
    "id": "75f35c41-274e-4047-bd13-42f7822a5651",
    "slug": "national-queer-trans-therapists-of-color-network",
    "externalUrl": "https://www.nqttcn.com/",
    "tags": [
      "mental-health",
      "social-services"
    ],
    "address": "Baltimore, MD 21211, USA",
    "phoneNumber": null,
    "country": "US",
    "provinceOrState": "MD",
    "city": "Baltimore",
    "latLng": [
      39.3289463,
      -76.63838319999999
    ],
    "email": "info@nqttcn.com",
    "socialMedia": {
      "facebookUrl": "Facebook-f",
      "twitterUrl": "Twitter",
      "instagramUrl": "Instagram"
    },
    "title": "राष्ट्रीय क्विअर आणि ट्रान्स रंगभेदी  चिकित्सक संघ",
    "description": "राष्ट्रीय क्विअर आणि ट्रान्स रंगभेदी  चिकित्सक संघ हा एक चिकित्सक न्याय संघटना आहे ज्याच्या ध्यासाने क्विअर आणि ट्रान्स रंगभेदी लोकांसठी मानसिक आरोग्याचे रूपांतर केले आहे. ते सामाजिक न्यायाच्या आंदोलनांच्या मध्यभागी होत असताना मानसिक आरोग्य क्षेत्रामध्ये काम करतात."
  },
  {
    "id": "79fdc5af-520b-45bc-a634-7af3d030db42",
    "slug": "shinesa",
    "externalUrl": "https://shinesa.org.au/",
    "tags": [
      "healthcare",
      "education-awareness",
      "mental-health",
      "social-services",
      "support-groups"
    ],
    "address": "64C Woodville Rd, Woodville SA 5011, Australia",
    "phoneNumber": "8300 5300",
    "country": "AU",
    "provinceOrState": "SA",
    "city": "Woodville",
    "latLng": [
      -34.87943560000001,
      138.536817
    ],
    "email": "info@shinesa.org.au",
    "socialMedia": null,
    "county": "Charles Sturt",
    "title": "SHINE SA",
    "description": "दक्षिण ऑस्ट्रेलियातील आरोग्य संस्था ज्यामुळे क्लिनिकल सेवा, लैंगिक आरोग्य सल्लागारी तसेच लैंगिक व प्रजनन स्वास्थ्य आणि संबंध साधारण कौशल्यांच्या शिक्षण आणि प्रशिक्षणांची पुरवठा होते. ती LGBTIQA+ समुदायासाठी समर्थन आणि समावेशी सेवा ही देते आहेत. हे वर कोणताही वाढीव आणि लिंग विविधता समुदायांच्या अधिकारांच्या सत्कारासाठी व ओळखासाठी उत्सव करणे आणि समर्थन करणे ह्यातही त्यांनी सहभागी आहेत."
  },
  {
    "id": "7a817d4c-02db-4c00-9988-6c2dbf63a7d4",
    "slug": "zoe-belle-gender-collective",
    "externalUrl": "https://zbgc.org.au/",
    "tags": [
      "education-awareness",
      "social-services",
      "support-groups"
    ],
    "address": "58 Mundy St, Bendigo VIC 3550, Australia",
    "phoneNumber": "0467 569 635",
    "country": "AU",
    "provinceOrState": "VIC",
    "city": "Bendigo",
    "county": "Greater Bendigo",
    "latLng": [
      -36.7605293,
      144.2860065
    ],
    "email": "contact@zbgc.org.au",
    "socialMedia": null,
    "title": "Zoe Belle लिंग संगठन",
    "description": "Zoe Belle लिंग संगठन हे एक ट्रान्स आणि लिंग विविधतेच्या मार्गदर्शनाखालील संगठन आहे ज्यामुळे व्यावसायिक प्रशिक्षण, कार्यशाळा, आणि LGBTQI+ समुदायासाठी मदत होते. मदत किंवा सहाय्य, समुदाय सेवांसाठी, कर्मचार्यांसाठी, कुटुंब आणि मित्रांसाठी, आणि ट्रान्स आणि लिंग विविधतेच्या व्यक्तींसाठी स्थानिक मूल्यांची सहाय्य साहित्य प्रदान करते. त्याने हालीच Transfemme हे एक स्वच्छंदी उपक्रम सुरू केले, ज्या मुळे trans स्त्रियांविरुद्ध सिस पुरुषांचे हिंसा विरोधात उपाय येतो."
  },
  {
    "id": "7fb1e1a6-bd81-4515-9aaa-70aea4580e55",
    "slug": "gender-diversity",
    "externalUrl": "https://genderdiversity.org",
    "tags": [
      "education-awareness",
      "healthcare",
      "youth-services",
      "support-groups",
      "parent-family-resources",
      "social-services",
      "non-binary",
      "transmasculine",
      "transfeminine"
    ],
    "address": "6523 California Ave SW #144, Seattle, WA 98136",
    "country": "US",
    "provinceOrState": "WA",
    "city": "Seattle",
    "county": "King County",
    "latLng": [
      47.544046,
      -122.387452
    ],
    "phoneNumber": "1-833-3GENDER",
    "email": "info@genderdiversity.org",
    "title": "लिंगीन विविधता",
    "description": "शिक्षण देऊन, जागरूकता वाढवून आणि मानवी अनुभवाच्या व्यापक रेंजीत अधिक अभिप्रेती देऊन, लिंगीन विविधता सर्व लिंगांच्या ओळख आणि अभिव्यक्तीच्या सर्व मुलांची आणि प्रौढांची सुखकरता सुधारीते. आम्ही नि:शंकित आणि भेदभावाने वागणाऱ्या वातावरणाची तयारी करतो शाळा, क्रीडा संघ, कामगारस्थळ आणि आरोग्यदेय व्यापारींसाठी, ज्या लोकांमध्ये ट्रान्सजेंडर आणि लिंगीन विविध व्यक्ती असतात."
  },
  {
    "id": "83a5458b-864a-4180-a176-b291ffbc7cfb",
    "slug": "nsw-treatment-and-rehabilitation-torture-trauma-survivors",
    "externalUrl": "https://www.startts.org.au/",
    "tags": [
      "healthcare",
      "mental-health",
      "social-services",
      "education-awareness"
    ],
    "address": "152/168 The Horsley Dr, Carramar NSW 2163, Australia",
    "phoneNumber": "+61 (0)2 9646 6700",
    "country": "AU",
    "provinceOrState": "NSW",
    "city": "Carramar",
    "county": "City of Fairfield",
    "latLng": [
      -33.8801011,
      150.9654668
    ],
    "email": "stts-startts@health.nsw.gov.au",
    "socialMedia": {
      "googleMapsUrl": null,
      "linkedinUrl": null,
      "facebookUrl": null,
      "youtubeUrl": null
    },
    "title": "येथील यंत्रणा आणि अपघातांच्या अनुभवांच्या उपचार आणि पुनर्वास साठी एनऍसडब्ल्यू सेवा",
    "description": "STARTTS म्हणजे सांस्कृतिक रितीनुसार मानसिक उपचार, समुदाय निर्देशने आणि सेवा साठी प्रशिक्षण प्रदान करते ज्याची उद्दीष्ट यंत्रणा आणि अपघातांच्या अनुभवांमुळे जितके शोधाला आलेले असे तितके लोकांना संपावण्यास मदत करण्यास मदत करण्यास आहे. त्यांचा उद्दिष्ट विविध लैंगिकतेच्या, लिंगांच्या, आणि शरीरांसाठी सुरक्षित आणि समर्थनार्थ वाहतुकीचे वातावरण तयार करण्याचा आहे, त्यातल्या शरणार्थ्यांना आणि आश्रय मागणार्‍यांना समाविष्ट करतात."
  },
  {
    "id": "878e809b-12aa-483f-be01-3c51a4d331d6",
    "slug": "national-center-for-transgender-equality",
    "externalUrl": "https://transequality.org",
    "tags": [
      "transmasculine",
      "non-binary",
      "transfeminine",
      "legal",
      "healthcare",
      "mental-health",
      "social-services",
      "youth-services",
      "support-groups",
      "parent-family-resources",
      "partner-resources",
      "education-awareness",
      "financial-aid-scholarships"
    ],
    "address": "1032 15th St NW #199, Washington, DC 20005, USA",
    "phoneNumber": "(202) 642-4542",
    "country": "US",
    "provinceOrState": "CA",
    "city": "Washington D.C.",
    "county": "District of Columbia",
    "latLng": [
      38.903438,
      -77.035037
    ],
    "email": "ncte@transequality.org",
    "socialMedia": {
      "blogUrl": "https://transequality.org/blog"
    },
    "title": "राष्ट्रीय ट्रान्सजेंडर समानता केंद्र",
    "description": "राष्ट्रीय ट्रान्सजेंडर समानता केंद्र ही संस्था ट्रान्सजेंडर लोकांची मान्यता आणि समजून घेणे साठी धोरणे आणि समाजाच्या मान्यतांमध्ये बदल करण्याच्या प्रयत्नांचा प्रतिपादन करते. नाटीसिटीई ट्रान्सजेंडर समाजातील मुद्द्यांची माहिती पुरवते, जसे की, वयोजन, हिंसाविरोध, रोजगार, कुटुंब, आरोग्य & एचआयव्ही, निवास & अपनिवास, आणि अधिक."
  },
  {
    "id": "87ef5091-eaa3-4740-b07f-11a889ead435",
    "slug": "transgender-law-center",
    "externalUrl": "https://transgenderlawcenter.org/",
    "tags": [
      "transmasculine",
      "transfeminine",
      "legal",
      "healthcare",
      "education-awareness"
    ],
    "address": "Oakland, CA 94612, USA",
    "phoneNumber": "510-587-9696",
    "country": "US",
    "provinceOrState": "CA",
    "city": "Oakland",
    "county": "Alameda County",
    "latLng": [
      37.8113159,
      -122.2682245
    ],
    "email": "info@transgenderlawcenter.org",
    "socialMedia": null,
    "title": "ट्रान्सजेंडर कायदा केंद्र",
    "description": "ट्रान्सजेंडर कायदा केंद्र ही सर्व लोकांसाठी आत्मनिर्भरतेसाठी सर्वात मोठी राष्ट्रीय ट्रान्स-संचालित संघटना आहे. या केंद्राने समृद्ध संसाधने आणि प्रकाशने ठेवत राहल्याने, केंद्र म्हणजे व्यक्तींना इतर जेंडर मान्य लोकांच्या सामान्य कायदेशीर आव्हानांचे आणि प्रश्नांचे समाधान करतात. TLC म्हणजेच ट्रान्सजेंडर कायदा केंद्र दीर्घकालीन, राष्ट्रीय, ट्रान्स-संचालित आंदोलनाकडे समुदायाला सक्ती देते."
  },
  {
    "id": "88a19313-994c-4908-a518-c09b531743e9",
    "slug": "deutsche-gesellschaft-fur-transidentitat-und-intersexualitat",
    "externalUrl": "https://dgti.org/",
    "tags": [
      "transmasculine",
      "transfeminine",
      "non-binary",
      "legal",
      "healthcare",
      "education-awareness"
    ],
    "address": null,
    "phoneNumber": null,
    "country": "DE",
    "provinceOrState": null,
    "city": null,
    "county": null,
    "latLng": null,
    "email": null,
    "socialMedia": {
      "yelpUrl": null,
      "googleMapsUrl": null,
      "facebookUrl": "https://www.facebook.com/dgti.eV",
      "twitterUrl": "https://twitter.com/dgti_eV",
      "instagramUrl": "https://www.instagram.com/dgti_ev/",
      "youtubeUrl": "https://www.youtube.com/channel/UCvPv3gwmnZcU5JT-06vxJrA"
    },
    "title": "जर्मन सोसायटी फॉर ट्रान्सआयडेंटिटी आणि इंटरसेक्स्युअलिटी",
    "description": "डोयचे गेसेल्शाफ्ट फूर ट्रान्सआयदेंटिटी उंद इंटरसेक्सुअलिटी (dgti) ही जर्मनीतील एक राष्ट्रीय व्यावसायिक संस्था आहे जी त्रांस, इंटर-जेंडर, नॉन-बाइनरी आणि एजेंडर व्यक्तींच्या स्वीकारणे आणि समानतेच्या वचनास त्याने प्रतिष्ठान केलेले आहे. dgti मित्र-च्या-मित्रची सल्लाग्रहण, कायदेशीर खात्री, बातम्या, आणि ट्रान्स* सल्लागार आणि वैद्यकीय तज्ज्ञांसाठी विविध संसाधन कार्यक्रमे पुरवते."
  },
  {
    "id": "8a206480-e41f-4bb6-9128-94d4b04cd997",
    "slug": "the-inner-circle",
    "externalUrl": "https://theinnercircle.org.za/",
    "tags": [
      "education-awareness",
      "support-groups",
      "spiritual"
    ],
    "address": "Lester Rd, Wynberg, Cape Town, 7824, South Africa",
    "phoneNumber": "+27 (0) 21 761 0037",
    "country": "ZA",
    "provinceOrState": "WC",
    "city": "Cape Town",
    "county": "City of Cape Town Metropolitan Municipality",
    "latLng": [
      -34.011883,
      18.469623
    ],
    "email": "admin@theinnercircle.org.za",
    "socialMedia": {
      "facebook": "https://www.facebook.com/pg/The-Inner-Circle-151896104833723/",
      "twitter": "https://twitter.com/TIC_SouthAfrica"
    },
    "town": "Wynberg",
    "title": "अंतर्गत वृत्त",
    "description": "लिंगी ओळख आणि लैंगिक आकर्षणावर आधारित मर्गक्रांत मुसलमानांना उपचार देण्याच्या लक्षात ठेवलेल्या वैश्विक मुस्लिम समुदाय. आत्मियतेच्या, शिक्षणाच्या आणि चळवळी निर्माणाच्या माध्यमातून"
  },
  {
    "id": "8ab7bb47-206d-4872-a3ca-e692ce2036ec",
    "slug": "florida-name-change-home",
    "externalUrl": "https://www.floridanamechange.org/",
    "tags": [
      "legal",
      "social-services"
    ],
    "address": null,
    "phoneNumber": null,
    "country": "US",
    "provinceOrState": "FL",
    "city": null,
    "county": null,
    "latLng": null,
    "email": null,
    "socialMedia": null,
    "title": "फ्लोरिडा नाव बदल होम",
    "description": "या वेबसाईटमध्ये फ्लोरिडातील त्यांचे नाव किंवा लिंग अद्ययावत करण्यासाठीच्या एका एका पायरीवर मार्गदर्शन दिलेले आहे. या पायर्‍यांमध्ये कोर्टात पिटीशन दाखल करणे, सोशल सिक्युरिटी कार्ड, ड्रायव्हर परवाना, पारपत्र आणि जन्म प्रमाणपत्र अद्ययावत करणे समाविष्ट आहे."
  },
  {
    "id": "91296a03-5c7f-4105-9ba7-2aa9e8bf5223",
    "slug": "parents-of-gender-diverse-children",
    "externalUrl": "https://www.pgdc.org.au/",
    "tags": [
      "parent-family-resources",
      "support-groups",
      "education-awareness",
      "mental-health",
      "youth-services"
    ],
    "address": null,
    "phoneNumber": "03 9663 6733",
    "country": "AU",
    "provinceOrState": null,
    "city": null,
    "county": null,
    "latLng": null,
    "email": "info@pgdc.org.au",
    "socialMedia": {},
    "title": "लैंगिक विविधता असलेल्या मुलांचे पालक",
    "description": "लैंगिक विविधता असलेल्या मुलांचे पालक ऑस्ट्रेलियातील लैंगिक अनेकता असलेल्या आणि ट्रान्सजेंडर असलेल्या मुलांच्या पालनाच्या काळात असलेल्या पालकांना समर्थन, कनेक्शन आणि स्त्रोत पुरवते. संघटना गोपनीयतेची आणि निर्णय न करणारी सहकारी, मासिक संगतना, ऑनलाईन पालक हब, आणि व्यावसायिक विकास आणि वक्ते पुरवते."
  },
  {
    "id": "92920c87-b8c4-4179-a98b-7c9b036c8b1a",
    "slug": "amsterdam-umc-kennis-en-zorgcentrum-genderdysforie",
    "externalUrl": "https://www.amc.nl/web/specialismen/genderdysforie.htm",
    "tags": [
      "healthcare",
      "education-awareness"
    ],
    "address": "De Boelelaan 1117, 1081 HV Amsterdam, Netherlands",
    "phoneNumber": "+31(0)20 444 0542",
    "country": "NL",
    "provinceOrState": "NH",
    "city": "Amsterdam",
    "county": "Amsterdam",
    "latLng": [
      52.3346104,
      4.8598083
    ],
    "email": "genderteam-poli@vumc.nl",
    "socialMedia": {
      "instagramUrl": "https://www.instagram.com/genderteam_amsterdamumc"
    },
    "town": "Amsterdam-Zuid",
    "title": "अ‍ॅम्स्टरडॅम UMC - जेंडर डिस्फोरिया साठी ज्ञान आणि व्यावसायिक केंद्र",
    "description": "अ‍ॅम्स्टरडॅम UMC मधील जेंडर डिस्फोरिया साठी ज्ञान आणि व्यावसायिक केंद्र हे वैद्यकीय उपचार आणि मनोवृत्ती सहाय्य प्रदान करणेत तज्ज्ञ आहे, ज्या लोकं म्हणतात की त्यांचे जन्म लिंग त्यांच्या ओळखेशी जुळत नाही. केंद्र मुलायांची वैविध्यता स्वागत करते, त्याच्या सेवा वैयक्तिक गरजांशी जुळवते आणि लिंग असंगतता चाचणीत त्याच्या निपुणतेसाठी जागतिकपातीवर मान्यता मिळते. तो ट्रान्सजेंडर व्यक्तींच्या समजुती आणि उपचारात सुधारांसाठी संशोधनही करतो आणि नवीन आरोग्य व्यावसायिकांना प्रशिक्षण देतो."
  },
  {
    "id": "9e09fcfd-eb5b-4dd9-825c-ae3c3c5ce940",
    "slug": "trans-lifeline-peer-support-and-resources",
    "externalUrl": "https://translifeline.org/",
    "tags": [
      "transmasculine",
      "non-binary",
      "transfeminine",
      "legal",
      "healthcare",
      "mental-health",
      "social-services",
      "support-groups",
      "education-awareness",
      "financial-aid-scholarships"
    ],
    "address": null,
    "email": null,
    "phoneNumber": "(877) 565-8860",
    "socialMedia": {
      "yelpUrl": null,
      "googleMapsUrl": null,
      "facebookUrl": "https://www.facebook.com/TransLifeline/",
      "twitterUrl": "https://twitter.com/TransLifeline",
      "instagramUrl": "https://www.instagram.com/translifeline/?hl=en",
      "youtubeUrl": null,
      "tiktokUrl": null,
      "twitchUrl": null,
      "patreonUrl": null
    },
    "title": "Trans Lifeline",
    "description": "Trans Lifeline ही एक ट्रान्स-नेतृत्वांकित संघटना आहे जी ट्रान्सजेंडर समुदायासाठी समान पुरस्कार आणि संसाधने प्रदान करते. समुदाय समर्थन, मायक्रोग्रांट्स आणि हॉटलाईनवर लक्ष केल्याने, ते ट्रान्स लोकांना त्या सॅमर्थन आणि संसाधनांची आवश्यकता असलेली प्रदान करण्याचे लक्ष करतात. Trans Lifeline म्हणजेच #SafeHotlines सारख्या उपक्रमांमार्गी ट्रान्स समुदायासाठी समर्थन करते."
  },
  {
    "id": "a0bc83c3-3566-4529-9560-bf98eb404461",
    "slug": "transliving-international",
    "externalUrl": "https://transliving.co.uk/main/",
    "tags": [
      "support-groups",
      "community-stories",
      "education-awareness",
      "clothing"
    ],
    "address": null,
    "phoneNumber": null,
    "country": null,
    "provinceOrState": null,
    "city": null,
    "county": null,
    "latLng": null,
    "email": null,
    "socialMedia": null,
    "title": "Transliving International",
    "description": "Transliving International ही ट्रांसजेंडर समुदायासाठी जागतिक समर्थन गट आहे, त्यामध्ये ऑनलाईन मागॅझिन, क्लब रात्री, कार्यक्रम, व शॉपिंग प्लॅटफॉर्म समाविष्ट आहे. ती सर्व लिंग विविधता व ट्रांस-लोकांच्या आवाजाला वाढवते, मदत, सल्ला, वैयक्तिक गोष्टी, व वैशिष्ट्ये प्रस्तुत करणारी."
  },
  {
    "id": "a453684e-c325-457f-8841-05c0adabbbc0",
    "slug": "the-trevor-project",
    "externalUrl": "https://www.thetrevorproject.org/",
    "tags": [
      "youth-services",
      "support-groups",
      "mental-health",
      "education-awareness"
    ],
    "address": "West Hollywood, CA 90069, USA",
    "email": null,
    "phoneNumber": "(212) 695-8650",
    "country": "US",
    "provinceOrState": "CA",
    "city": "West Hollywood",
    "county": "Los Angeles County",
    "latLng": [
      34.0931603,
      -118.3783347
    ],
    "socialMedia": {
      "yelpUrl": null,
      "googleMapsUrl": null,
      "facebookUrl": "https://www.facebook.com/TheTrevorProject",
      "twitterUrl": "https://twitter.com/trevorproject",
      "instagramUrl": "https://www.instagram.com/trevorproject/",
      "youtubeUrl": "https://www.youtube.com/thetrevorproject",
      "tiktokUrl": "https://www.tiktok.com/@trevorproject",
      "twitchUrl": null,
      "patreonUrl": null
    },
    "title": "द ट्रेव्हर प्रोजेक्ट",
    "description": "द ट्रेव्हर प्रोजेक्ट हे एक अमेरिकन नॉन-प्रॉफिट संघटना आहे, ज्याने LGBTQ+ तरुणांना आत्महत्या रोखणारी सेवा प्रदान केली आहे. या साइटवर ट्रानसजेंडर समुदायासाठी मूल्यवान संसाधने उपलब्ध केली आहेत, ज्यात आपत्ती निवारण आणि आत्महत्या रोखणारी लायफलाइन, ट्रेव्हरचॅट, आणि ट्रेव्हरटेक्स्ट, मानसिक आरोग्य, सामाजिक सेवा, आणि समर्थन समूहांच्या मार्गदर्शनासह असलेली आहेत."
  },
  {
    "id": "a4f258ec-17b7-4477-bd90-a7580ab66086",
    "slug": "gender-dysphoria-1177-vaardguiden",
    "externalUrl": "https://www.1177.se/liv--halsa/konsidentitet-och-sexuell-laggning/konsdysfori/",
    "tags": [
      "healthcare"
    ],
    "address": null,
    "phoneNumber": null,
    "country": "SE",
    "provinceOrState": null,
    "city": null,
    "county": null,
    "latLng": null,
    "email": null,
    "socialMedia": null,
    "title": "लिंग असंतुष्टता - 1177 Vårdguiden",
    "description": "स्वीडनमधील 1177 आरोग्य मार्गदर्शकाने पुरोगामी संसाधने प्रदान केलेली लिंग असंतुष्टतेवरची सम्पूर्ण माहिती, ती काय असते, ती कसी वाटते, कशासाठी मदत मागण्याचे विविध उपचार विकल्प. ते लिंग असंतुष्टतेस अनुभव करणार्यांसाठी विस्तृत माहिती प्रदान करते आणि त्यांच्या प्रवासात सहाय्य करते."
  },
  {
    "id": "a58acbca-7d7d-4c6d-8d5f-f1a281e0f8b9",
    "slug": "pronoun-dressing-room",
    "externalUrl": "http://www.pronouns.failedslacker.com/",
    "tags": [
      "non-binary",
      "transmasculine",
      "transfeminine",
      "education-awareness"
    ],
    "address": null,
    "phoneNumber": null,
    "country": null,
    "provinceOrState": null,
    "city": null,
    "county": null,
    "latLng": null,
    "email": null,
    "socialMedia": null,
    "title": "सर्वनाम ड्रेसिंग रूम",
    "description": "सर्वनाम ड्रेसिंग रूम हे एक असा ऑनलाइन स्थळ पुरवतो जिथे व्यक्ती वेगवेगळे सेट आजमावू शकतात आणि त्यातील सर्वनामांची शोध घेऊ शकतात, जे त्यांच्यासाठी योग्य असतील. वेबसाइट ही ट्रान्सजेंदर समुदायासाठी सर्वनाम निवडण्यात सोपायी असलेली निर्णय घेण्याची सोय देते, जेणेकरून ते पाहू शकतात की वेगवेगळ्या संदर्भात वेगवेगळे सर्वनाम कसे दिसतील."
  },
  {
    "id": "ab058b91-49cf-4733-b3a3-47ea59b31a78",
    "slug": "a-place-for-marsha",
    "externalUrl": "https://www.aplaceformarshaofficial.org/",
    "tags": [
      "transmasculine",
      "non-binary",
      "transfeminine",
      "legal",
      "mental-health",
      "social-services",
      "support-groups",
      "education-awareness",
      "financial-aid-scholarships",
      "community-stories"
    ],
    "email": "info@aplaceformarshaofficial.org",
    "socialMedia": {
      "tiktok": "https://www.tiktok.com/@aplaceformarsha"
    },
    "title": "मार्शा साठी एक ठिकाण",
    "description": "मार्शा साठी एक ठिकाण हे अधिक व प्रतिसादात्मक म्हणजेच अधिक धोकादायक राज्यांतील ट्रान्स व्यक्तींची आणि कुटुंबियांची मदत करणार्या अनेक सुरुवातीच्या प्रकल्पांपैकी एक आहे. APFM त्याचे प्रवास मार्च 2023 मध्ये संपूर्ण देशातील विरोधक ट्रान्स कायद्यांच्या वाढीच्या प्रतिसादाने सुरु केले. APFM आता लाल राज्यातील शरणार्थ्यांना रुममेट म्हणून जोडण्यावर, एकैकाने घरगुती विचारलेल्या, केंद्रीभूत करते."
  },
  {
    "id": "af3483e3-d7f7-49d7-a4e9-b70e566bee98",
    "slug": "good-hope-metropolitan-community-church",
    "externalUrl": "https://www.goodhopemcc.org",
    "tags": [
      "spiritual"
    ],
    "address": "18 Belmont Rd, Rondebosch, Cape Town, 7700, South Africa",
    "phoneNumber": null,
    "country": "ZA",
    "provinceOrState": "WC",
    "city": "Cape Town",
    "county": "City of Cape Town Metropolitan Municipality",
    "latLng": [
      -33.9605258,
      18.474311
    ],
    "email": "secretary@goodhopemcc.org",
    "socialMedia": {
      "facebook": "https://www.facebook.com/goodhopemcc"
    },
    "town": "Rondebosch",
    "title": "GOOD HOPE महानगरीय समुदायी चर्च",
    "description": "जेशू ख्रिस्ताच्या सिद्धांतांवर अडकलेल्या तत्त्वज्ञानिक प्रगतीशील आणि समावेशक क्रैस्तव समुदाय ज्याने विविधतेची उत्सव मनावे आणि सर्वांसाठी सुरक्षित, निर्दोष अंतराव कहां शकतो. केप टाऊन, दक्षिण आफ्रिकेमधील समावेशक क्रैस्तव मंडळाचा भाग आहे आणि याचा महानगरीय समुदायी चर्च (MCC) म्हणजेच मोठ्या आंतरराष्ट्रीय धर्मविरोधातील भाग."
  },
  {
    "id": "b2741990-69b4-4fbd-98e7-933b8932425f",
    "slug": "transfamily",
    "externalUrl": "https://www.transfamily.org.au/",
    "tags": [
      "support-groups",
      "parent-family-resources",
      "community-stories",
      "education-awareness"
    ],
    "address": null,
    "phoneNumber": null,
    "country": null,
    "provinceOrState": null,
    "city": null,
    "county": null,
    "latLng": null,
    "email": null,
    "socialMedia": {
      "facebookUrl": "https://www.facebook.com/Transfamily-Australia-126186690851106/"
    },
    "title": "ट्रान्सफॅमिली",
    "description": "ट्रान्स आणि लिंग विविध व्यक्तींच्या पालकांच्या, भावंडांच्या, विस्तृत कुटुंब आणि मित्रांसाठीचा मित्र समर्थन गट. त्यात उपकरणे, कार्यक्रमे, आणि समुदाय कथांसाठीचा वेधदेखभाग उपलब्ध आहे. त्यातील ट्रान्सफ़ॅमिली पुस्तक म्हणजेच ट्रान्सजेंडर समुदायाबद्दल उपयुक्त माहिती आणि तिचे अंतर्दृष्टी प्रदान करते."
  },
  {
    "id": "b6955ff7-83b4-464f-8be8-72a50dc6a878",
    "slug": "transvoicelessons",
    "externalUrl": "https://www.transvoicelessons.com/",
    "tags": [
      "voice-training"
    ],
    "address": null,
    "phoneNumber": null,
    "country": null,
    "provinceOrState": null,
    "city": null,
    "county": null,
    "latLng": null,
    "email": null,
    "socialMedia": {
      "yelpUrl": null,
      "googleMapsUrl": null,
      "facebookUrl": null,
      "twitterUrl": null,
      "instagramUrl": null,
      "youtubeUrl": "https://www.youtube.com/c/transvoicelessons",
      "tiktokUrl": null,
      "twitchUrl": null,
      "patreonUrl": "https://www.patreon.com/transvoicelessons/posts"
    },
    "title": "TransVoiceLessons",
    "description": "TransVoiceLessons हे ट्रान्सजेंडर व नॉन-बायनरी व्यक्तींसाठी उच्च गुणवत्तेच्या स्वर नियंत्रण व मुक्ती सेवा पुरवते ज्यांना पुरुषांसमान, स्त्रीसमान किंवा उभयलिंगी असायला इच्छित आहे."
  },
  {
    "id": "b86b3697-6f65-4fd1-8506-e2ce879a614c",
    "slug": "working-it-out-tasmania",
    "externalUrl": "https://www.workingitout.org.au/",
    "tags": [
      "non-binary",
      "transmasculine",
      "transfeminine",
      "mental-health",
      "social-services",
      "youth-services",
      "support-groups",
      "education-awareness"
    ],
    "address": null,
    "phoneNumber": null,
    "country": "AU",
    "provinceOrState": "TAS",
    "city": null,
    "county": null,
    "latLng": null,
    "email": null,
    "socialMedia": null,
    "title": "गोष्टी निघवणे",
    "description": "गोष्टी निघवणे तासमानियाची लैंगिकता, लिंग आणि इंटरसेक्स स्थितीची मदत आणि शिक्षण सेवा आहे. ती LGBTIQ+ तासमानियन साठी मदत आणि वक्तव्य सेवा प्रदान करते आणि शाळांमध्ये, कामगार संघात, सरकारी आणि असरकारी संघटनांमध्ये शिक्षण आणि प्रशिक्षण कार्यक्रमे सादर करते."
  },
  {
    "id": "b933717d-90e3-4aff-a61f-bd1fd1f2893b",
    "slug": "thorne-harbour-health",
    "externalUrl": "https://thorneharbour.org/",
    "tags": [
      "healthcare",
      "support-groups",
      "mental-health",
      "social-services",
      "education-awareness"
    ],
    "address": null,
    "phoneNumber": null,
    "country": null,
    "provinceOrState": null,
    "city": null,
    "county": null,
    "latLng": null,
    "email": null,
    "socialMedia": null,
    "title": "Thorne Harbour Health",
    "description": "लैंगिक, लिंग आणि स्वतंत्रता विविध समुदायांसाठी आरोग्य आणि कल्याण सेवा पुरवणारी एक LGBTIQ+ समुदाय-नियंत्रित संगठन, सह HIV समर्थन आणि रोखण, सल्लागारी, आणि कुटुंब हिंसा सेवा समाविष्ट."
  },
  {
    "id": "ba3e158a-53b6-4dc5-a220-4a065859aa7f",
    "slug": "queer-lexikon",
    "externalUrl": "https://queer-lexikon.net/",
    "tags": [
      "transmasculine",
      "non-binary",
      "transfeminine",
      "legal",
      "healthcare",
      "mental-health",
      "support-groups",
      "education-awareness",
      "community-stories"
    ],
    "address": null,
    "phoneNumber": null,
    "country": null,
    "provinceOrState": null,
    "city": null,
    "county": null,
    "latLng": null,
    "email": null,
    "socialMedia": {
      "twitterUrl": "fab fa-twitter",
      "facebookUrl": "fab fa-facebook",
      "instagramUrl": "fab fa-instagram",
      "youtubeUrl": "fab fa-youtube",
      "patreonUrl": "fab fa-patreon",
      "tumblrUrl": "fab fa-tumblr",
      "linkedinUrl": "fab fa-linkedin-in",
      "emailUrl": "fas fa-envelope"
    },
    "title": "Queer Lexikon",
    "description": "Queer Lexikon ही एक ऑनलाईन स्त्रोत आहे जी क्वीर समाजासाठी व्यापक माहिती आणि समर्थन पुरवते. लैंगिक, प्रेम, लिंगीन विविधतेपासून मानसिक आरोग्य आणि समर्थन गटांपर्यंत विविध विषयांच्या वर्णन करणारी. हे शिक्षण, जागरूकता आणि समुदायीच्या गोष्टीसाठी एक हब आहे."
  },
  {
    "id": "bc49f848-fa04-47ff-af81-cb500214ce61",
    "slug": "transformering-se",
    "externalUrl": "https://transformering.se/",
    "tags": [
      "transmasculine",
      "non-binary",
      "transfeminine",
      "legal",
      "healthcare",
      "mental-health",
      "social-services",
      "youth-services",
      "support-groups",
      "parent-family-resources",
      "partner-resources",
      "community-stories",
      "education-awareness"
    ],
    "address": "Stockholm, Sweden",
    "phoneNumber": null,
    "country": "SE",
    "provinceOrState": "Stockholm County",
    "city": "Stockholm",
    "latLng": [
      59.32932349999999,
      18.0685808
    ],
    "email": null,
    "socialMedia": {
      "yelpUrl": null,
      "googleMapsUrl": null,
      "twitterUrl": "https://twitter.com/rfslungdom",
      "instagramUrl": "https://www.instagram.com/rfsl_official",
      "facebookUrl": "http://www.facebook.com/transformering"
    },
    "title": "Transformering.se",
    "description": "RFSL Ungdom आणि RFSL द्वारे संचालित स्वीडिश संसाधन हब ज्यामध्ये लिंग परिवर्तन आणि लिंग परिचयाशी संबंधित माहिती आणि समर्थन दिलेली आहे. आशयात हक्क, संबंध, आणि लिंग पुष्टीकरण देखभाल कसे काम करते यासह आहे. इतकी म्हणता येईल की लिंग परिवर्तन करणारे, वैयक्तिक लिंग अनुभव असणारे, किंवा त्यांचे लिंग परिचय / व्यक्तिमत्व चाचणी करणारे, तसेच त्यांचे प्रियांसाठी, प्रामाणिक, किंवा अभ्यासकर्त्यांसाठी तयार केलेले आहे ज्यांनी त्यांला समर्थन दिलेले आहे."
  },
  {
    "id": "be017772-af87-4920-ae62-1a3e961d216a",
    "slug": "transamsterdam",
    "externalUrl": "https://www.transamsterdam.nl/",
    "tags": [
      "artists-creators",
      "education-awareness"
    ],
    "address": "Linnaeusstraat 89, 1093 EK Amsterdam, Netherlands",
    "phoneNumber": null,
    "country": "NL",
    "provinceOrState": "NH",
    "city": "Amsterdam",
    "county": "Amsterdam",
    "latLng": [
      52.35914529999999,
      4.9263607
    ],
    "email": "info@transamsterdam.nl",
    "socialMedia": {
      "linktr": "linktr.ee/transamsterdam"
    },
    "town": "Amsterdam-Oost",
    "title": "TransAmsterdam",
    "description": "TransAmsterdam ही एक ट्रान्स संगठना आहे जी आम्स्टरडॅममधील कला, संस्कृती आणि जीवनशैलीवर केंद्रित आहे. ती विविध स्तंभांद्वारे ट्रान्सजेंडर समुदायाला समर्थन देते. यात Trans & Friends कॅफे, InClusion आणि इतर कार्यक्रमांद्वारे भेटीची संधी तयार करणे असलेले आहे. तसेच workshops, विषयवस्तु बैठकी, आणि Trans Art School येथे थिएटर निर्मितीद्वारे प्रतिभा विकासाची प्रोत्साहन देते. शेवटी, ती ट्रान्सजेंडर, अबायनरी कलाकारांसाठी आणि त्यांनी कला आणि सांस्कृतिक प्लॅटफॉर्म प्रदान करते."
  },
  {
    "id": "be5fc820-136d-4e7f-a3b5-ae6d103ef1ad",
    "slug": "gender-centre",
    "externalUrl": "https://gendercentre.org.au/",
    "tags": [
      "transmasculine",
      "transfeminine",
      "non-binary",
      "mental-health",
      "social-services",
      "support-groups",
      "education-awareness",
      "healthcare"
    ],
    "address": null,
    "phoneNumber": "02 9519 7599",
    "country": "AU",
    "provinceOrState": null,
    "city": "Sydney",
    "county": null,
    "latLng": null,
    "email": null,
    "socialMedia": null,
    "title": "लिंग केंद्र ईन्क.",
    "description": "लिंग केंद्र ईन्क. हे लिंग परिचयाची शोध आणि लिंगीय अस्वस्थतेच्या कमीकरणास मदत करणारी विशेषज्ञतेची विविध सेवा प्रदान करत आहे. हे प्रत्येक तपशीली यात्रेच्या प्रत्येक टप्प्यावर तांत्रिक आणि लिंगाचे व्यक्त करणार्‍या लोकांच्या मदतीस आहे ज्यांनी त्यांच्या मूळ आत्मसात्ता स्पष्ट केलेली आहे. त्यातली आहेत वासयात्राची सुविधा, प्रकरण व्यवस्थापन, शिक्षण आणि प्रशिक्षण, मानसिक स्वास्थ्य सेवा आणि समूह., बातम्या आणि संसाधने."
  },
  {
    "id": "bfc56737-9f48-4344-8a0e-22ae450d5250",
    "slug": "learning-with-love-the-2023-pflag-national-convention",
    "externalUrl": "https://pflag.org/",
    "tags": [
      "education-awareness",
      "support-groups",
      "parent-family-resources",
      "community-stories"
    ],
    "address": "Washington, DC, USA",
    "phoneNumber": null,
    "country": "US",
    "provinceOrState": "DC",
    "city": "Washington",
    "county": "District of Columbia",
    "latLng": [
      38.9071923,
      -77.0368707
    ],
    "email": null,
    "socialMedia": null,
    "title": "प्रेमाने शिकणे: 2023 पीएफएलएजी राष्ट्रीय संमेलन",
    "description": "पीएफएलएजीने संघटित केलेला एक चार दिवसांचा कार्यक्रम, कनेक्ट करण्यास, नेटवर्किंगसाठी, शिकण्यासाठी आणि अनुभव सामायिक करण्यासाठी. संमेलनात एलजीबीटीक्यू + लोकांसाठी आणि त्यांना प्रेम करणार्‍या लोकांसाठी एक स्नेही, न्यायस्पष्ट आणि स्वीकारलेली जग तयार करण्याच्या त्यांच्या मिशनच्या समर्थनार्थ कार्यशाळा, पॅनल आणि प्रस्तुतिका आयोजित केल्या जातील."
  },
  {
    "id": "c23736ad-03dc-41dd-b8f9-4f64b2727cdc",
    "slug": "freedom-centre-wa",
    "externalUrl": "https://www.freedom.org.au/",
    "tags": [
      "youth-services",
      "mental-health",
      "social-services",
      "support-groups",
      "education-awareness",
      "parent-family-resources"
    ],
    "address": null,
    "phoneNumber": null,
    "country": "AU",
    "provinceOrState": "WA",
    "city": null,
    "county": null,
    "latLng": null,
    "email": null,
    "socialMedia": {
      "facebookUrl": "https://www.facebook.com/FreedomCentrePerth",
      "instagramUrl": "https://www.instagram.com/freedom_centre/"
    },
    "title": "स्वातंत्र्य केंद्र",
    "description": "स्वातंत्र्य केंद्रने लिंब्सोव्हीआ+, तरुण माणसांसाठी एक प्रचंड सहाय्य सेवा एकीकृत केलेली आहे, त्यात ड्रॉप-इन सत्र, समुदाय विकास, मनोपचार आणि अधिक असे आहे. ते सर्व लिंब्सोव्हीआ+ तरुण माणसांना समाविष्ट, जोडलेले आणि सन्मानित वाटण्यासाठी काम करतात. ते माता-पिता, प्रामाणिक, समुदाये आणि संघटनांना प्रशिक्षण आणि मार्गदर्शन देतात."
  },
  {
    "id": "c4437a30-c2e0-4672-8f37-74de08818f97",
    "slug": "point-of-pride",
    "externalUrl": "https://www.pointofpride.org/",
    "tags": [
      "transmasculine",
      "transfeminine",
      "non-binary",
      "healthcare",
      "financial-aid-scholarships"
    ],
    "address": null,
    "phoneNumber": null,
    "country": null,
    "provinceOrState": null,
    "city": null,
    "county": null,
    "latLng": null,
    "email": null,
    "socialMedia": null,
    "title": "गर्वाचा बिंदू",
    "description": "गर्वाचा बिंदू आरोग्य आणि कल्याणाच्या काळजीला आवश्यक असलेल्या ट्रान्स लोकांना आर्थिक मदत आणि प्रत्यक्ष सहाय्य प्रदान करते. मदतीच्या कार्यक्रमांमध्ये वार्षिक ट्रान्सजेंडर सर्जरी फंड्स, HRT ऍक्सेस फंड्स, इलेक्ट्रोलिसिस सहाय्य आणि मोफत छाती बाइंडर्स आणि फेम शेपवेअर प्रविष्टीचा प्रविष्टी आहे ज्या ट्रान्स लोकांना सुरक्षितपणे सापडत नाही किंवा त्यांची किंमत भरता येत नाही."
  },
  {
    "id": "c6a77c4c-7aa3-47b3-b385-8573e1ba3a78",
    "slug": "transmann-ev",
    "externalUrl": "https://transmann.de/",
    "tags": [
      "transmasculine",
      "non-binary",
      "healthcare",
      "mental-health",
      "support-groups",
      "education-awareness"
    ],
    "email": "info@transmann.de",
    "socialMedia": {},
    "title": "TransMann e.V.",
    "description": "TransMann e.V. म्हणजेच एक स्वयंसेवी, नफाच्या संघटना आहे जी सर्व स्त्री-पुरुष (FzM/FtM) Trans* आणि Inter*-लोकांसाठी जर्मनीतील व्यापक मदत केली आहे. सेवांमध्ये समुह बैठकी, संगणकवरील माहिती आणि संसाधने, समरस ते समरस सल्लागार, शैक्षणिक साहित्य आणि सार्वजनिक उपस्थिती असे. ते Trans*-अनुभवी डॉक्टर आणि उपचारांची राष्ट्रव्यापी डेटाबेसही ठेवतात. त्यांची प्रमुख वाचक वर्ग म्हणजेच FzM-Trans* आणि Inter* लोक असे, परंतु ते कुटुंबीय, मित्र, साथीदार, शैक्षणिक संस्था, आणि नियोजकांला त्यांचे संसाधन आणि मदत प्राप्त करण्यास म्हणजेच ते समर्पीत आहेत."
  },
  {
    "id": "cd48f2d0-8241-4fa5-a0aa-dc3cd3d386e8",
    "slug": "rainbowrailroadorg",
    "externalUrl": "https://RainbowRailroad.org",
    "tags": [
      "transfeminine",
      "non-binary",
      "transmasculine",
      "legal",
      "social-services"
    ],
    "title": "RainbowRailroad.org",
    "description": "ज्या एलजीबीटीक्यू+ व्यक्तींची जगतीक तत्काळ उत्पीडन आणि हिंसा घडत असलेल्या अहोवती त्यांना मदतीसाठी आणि त्यांचा प्रतिपालन करण्यासाठी समर्पित एक महत्त्वाचं ऑनलाइन प्लॅटफॉर्म. अस्थिर प्रतिबद्धतेसह या वेबसाइट मदत करण्यासाठी, आपत्तीवेळी मदत, आणि सुरक्षित सुरंगीतल्या सुरक्षिततेचे मार्ग आपल्याला आणि मरणापासून. स्थानिक संगठनांशी भागीदारी आणि दयाळु समर्थकांच्या नेटवर्कद्वारे, RainbowRailroad.org व्यक्तींना हिंसेपासून पलायन करण्याची आणि शरण शोधण्याची समर्थन, कायदाशास्त्रीय मदत, आणि पुनर्वसनाची मदत प्रदान करण्यासाठी थकबाकीराहिले. मानवी अधिकारांचे स्वीकार, आयुष्यांची वाचवा, आणि अधिक समावेशी जग वाढविण्याद्वारे RainbowRailroad.org हे एलजीबीटीक्यू+ व्यक्तींसाठी सुरक्षा आणि स्वातंत्र्य शोधणार्‍या ज्योतीचे आशा आणि सुरक्षा देणारे दिवे म्हणून कार्य करते."
  },
  {
    "id": "cfb4d1a4-0142-4dfa-b152-8e577885e98c",
    "slug": "blaq-aboriginal-corporation",
    "externalUrl": "https://blaq.org.au/",
    "tags": [
      "community-stories",
      "education-awareness",
      "social-services",
      "support-groups"
    ],
    "address": "Redfern NSW 2016, Australia",
    "phoneNumber": null,
    "country": "AU",
    "provinceOrState": "NSW",
    "city": "Redfern",
    "county": "City of Sydney",
    "latLng": [
      -33.892215,
      151.205873
    ],
    "email": "admin@blaq.org.au",
    "socialMedia": null,
    "title": "BlaQ मूलवासी कॉर्पोरेशन",
    "description": "BlaQ मूलवासी कॉर्पोरेशन ही एक समुदाय संगठन आहे, ज्याचे अभिप्रेत करणे आणि मूलवासी आणि तोरेस स्ट्रेट द्वीपवासी LGBTQ+SB समुदायाची सक्षमता वाढवणे आणि त्यांच्यासाठी समावेश, समज, अभिप्रेत आणि प्रतिनिधित्वाच्या माध्यमातून."
  },
  {
    "id": "d21dfad9-22c7-4a42-9658-d1c573100c33",
    "slug": "baby-making-for-everybody",
    "externalUrl": "https://www.babymakingforeverybody.com/",
    "tags": [
      "parent-family-resources",
      "education-awareness"
    ],
    "address": null,
    "phoneNumber": null,
    "country": null,
    "provinceOrState": null,
    "city": null,
    "county": null,
    "latLng": null,
    "email": null,
    "socialMedia": null,
    "title": "प्रत्येकासाठी बाळ निर्माण",
    "description": "LBGTQ+ आणि एकटे माता-पिते साठी पारंपारिक हेटरोसेक्सुअल-न्यूक्लियर-कुटुंब नमुन्याच्या बाहेरील विविध कुटुंब निर्माण पद्धतींची मनानी आणि कसे करावे ह्याचा मार्गदर्शन. ही पुस्तक एका चरणावलीच्या मार्गदर्शनासोबत वैयक्तिक चरित्रांचे सामावेश करते, परिप्रेक्ष्यी माता-पितांना त्यांच्या कुटुंबांचे विस्तार कसे करावे ह्याचे एक नकाशा प्रदान करते."
  },
  {
    "id": "d59c0a9f-14ff-4c55-94d6-82313925be14",
    "slug": "the-mckenzie-project",
    "externalUrl": "https://www.themckenzieproject.org/",
    "tags": [
      "transmasculine",
      "non-binary",
      "transfeminine",
      "legal",
      "healthcare",
      "mental-health",
      "social-services",
      "youth-services",
      "support-groups",
      "education-awareness"
    ],
    "address": "8390 W Flagler St STE 201, Miami, FL 33144, USA",
    "email": "Info@TheMcKenzieProject.org",
    "phoneNumber": "305-846-3186",
    "country": "US",
    "provinceOrState": "FL",
    "city": "Miami",
    "county": "Miami-Dade County",
    "latLng": [
      25.769445,
      -80.3321284
    ],
    "socialMedia": {
      "yelpUrl": null,
      "googleMapsUrl": null,
      "facebookUrl": null,
      "twitterUrl": null,
      "instagramUrl": null,
      "youtubeUrl": null,
      "tiktokUrl": null,
      "twitchUrl": null,
      "patreonUrl": null
    },
    "title": "मॅकेंझी प्रकल्प",
    "description": "लिंग न्याय बळीवाण करणार्या आणि ट्रान्सज्ञान समुदायाची सेवा करणार्या सेवांची, कार्यक्रमांची व कार्यक्रमांची वयोमय संसाधने प्रस्तुत करणारा प्रकल्प. स्वास्थ्यसेवा, कायदेशीर मदत, मानसिक आरोग्य सेवा आणि अधिक असलेल्या समर्थन सेवांची आणि संसाधनांची समावेश."
  },
  {
    "id": "d7378cc4-7726-4de1-8427-8203cb9b61ad",
    "slug": "east-bay-trans-queer-counseling",
    "externalUrl": "https://www.eastbaytranscounseling.org/",
    "tags": [
      "transmasculine",
      "non-binary",
      "transfeminine",
      "mental-health",
      "social-services",
      "youth-services",
      "education-awareness"
    ],
    "email": "eastbaytranscounseling@gmail.com",
    "address": "3099 Telegraph Ave, Berkeley, CA 94705, USA",
    "phoneNumber": "781-775-7802",
    "country": "US",
    "provinceOrState": "CA",
    "city": "Berkeley",
    "county": "Alameda County",
    "latLng": [
      37.8538725,
      -122.2596505
    ],
    "socialMedia": {
      "yelpUrl": null,
      "googleMapsUrl": null,
      "facebookUrl": null,
      "twitterUrl": null,
      "instagramUrl": null,
      "youtubeUrl": null,
      "tiktokUrl": null,
      "twitchUrl": null,
      "patreonUrl": null
    },
    "title": "पूर्व बे ट्रान्स आणि क्विअर सल्लागार",
    "description": "पूर्व बे ट्रान्स आणि क्विअर सल्लागार यांनी छुट्यावर सेवा प्रदान करण्याचे आव्हान केले आहे ज्यामध्ये समाविष्ट आहे: वैयक्तिक उपचार बर्कली सेंट्रल्लोकेटेड, CA मध्ये स्थानिकतेच्या माध्यमातून लिंग संस्कार औषधे आणि शल्यक्रियांसाठी सिफारस पत्र प्रोफेशनल ट्रेनिंग मानसिक आरोग्य प्रदाता, विद्यार्थी, औषधे आणि शल्यक्रियांसाठी सिफारस पत्र, विद्यार्थी, आणि कामगारांसाठी. सॅम डेव्हिस म्हणजे एक ट्रान्सजेंडर, जेंडरक्विअर लायसेन्स्ड क्लिनिकल सोशल वर्कर (LCSW) ज्यांचा विशेषज्ञता ट्रान्स, क्विअर, जेंडरक्विअर, आणि जेंडर-नॉनकन्फॉर्मिंग तरुणांच्या साथी काम करण्यात आहे. त्यांना पूर्व बे मधील मानसिक आरोग्य पुरवठादारांमध्ये 16 वर्षांचा अनुभव आहे, यामध्ये समर्थन समूह सुविधा, LGBTQI संमेलनांमधील समुदाय शिक्षण, आणि अलामेडा काउंटीसाठी गंभीरपणे वंचित माणसांच्या साथी वैयक्तिक अभ्यास आणि संकट सल्लागार सह 9 वर्षे आहेत. ते वंचित व्यक्तींच्या मतदारांमध्ये दीर्घकाळीन आयोजक आहेत."
  },
  {
    "id": "dcb18ebe-596d-4d3e-a409-542f06a109a7",
    "slug": "seahorse-victoria-club",
    "externalUrl": "https://seahorsevic.com.au/",
    "tags": [
      "support-groups",
      "community-stories",
      "friendly-businesses"
    ],
    "address": "St Kilda VIC 3182, Australia",
    "phoneNumber": "0401 455 198",
    "country": "AU",
    "provinceOrState": "VIC",
    "city": "St Kilda",
    "county": "Port Phillip",
    "latLng": [
      -37.864,
      144.982
    ],
    "email": "seahorsevic@gmail.com",
    "socialMedia": {
      "yelpUrl": null,
      "googleMapsUrl": null
    },
    "title": "सीहॉर्स विक्टोरिया क्लब",
    "description": "1975 मध्ये स्थापना झालेल्या सीहॉर्स क्लब विक्टोरियाने ट्रान्सजेंडर समुदायांसाठी संसाधने, समुदाय सेवा आणि समर्थन प्रदान केले आहेत. त्यात सेवांच्या एक ट्रान्स-अनुकूल निर्देशिका आणि सदस्यांना जोडण्यासाठी येणार्या ऑनलाइन प्लॅटफॉर्माची समावेशकता आहे."
  },
  {
    "id": "e20d344a-9e07-44b6-8b9e-c21554a1cda6",
    "slug": "a-complete-guide-to-transmasculine-reproduction",
    "externalUrl": "https://transmasculinereproduction.sites.ucsc.edu/",
    "tags": [
      "transmasculine",
      "healthcare",
      "education-awareness",
      "parent-family-resources",
      "support-groups"
    ],
    "address": null,
    "phoneNumber": null,
    "country": null,
    "provinceOrState": null,
    "city": null,
    "county": null,
    "latLng": null,
    "email": null,
    "socialMedia": null,
    "title": "ट्रान्समॅस्क्युलिने प्रजननाची संपूर्ण मार्गदर्शिका",
    "description": "ट्रान्समॅस्क्युलिने संतती, गर्भावस्था, प्रसूती काळ, स्तनपान, आणि पालकत्वावर माहिती देणाऱ्या व्यापक मार्गदर्शिका. या संसाधनात ट्रांस-समर्थक आरोग्य सेवा प्रदाते, संशोधित वारंवार विचारलेल्या प्रश्नांचा समावेश असलेल्या विविध संसाधने आणि आपल्या पालन क्षेत्री ट्रान्समस्क्युलिने व्यक्तींचे शिक्षण आणि समर्थन केलेली अधिक."
  },
  {
    "id": "e51c019c-8dfe-498e-b82e-4263a8f747e8",
    "slug": "equality-florida",
    "externalUrl": "https://www.eqfl.org/",
    "tags": [
      "legal",
      "healthcare",
      "education-awareness"
    ],
    "address": null,
    "country": "US",
    "provinceOrState": "FL",
    "city": "St. Petersburg",
    "county": null,
    "latLng": null,
    "email": null,
    "phoneNumber": "813-870-3735",
    "socialMedia": {
      "yelpUrl": null,
      "googleMapsUrl": null,
      "facebookUrl": "https://www.facebook.com/equalityfl/",
      "twitterUrl": "https://twitter.com/EqualityFlorida",
      "instagramUrl": "https://www.instagram.com/equalityfl/",
      "youtubeUrl": null,
      "tiktokUrl": null,
      "twitchUrl": null,
      "patreonUrl": null
    },
    "title": "समानता फ्लोरिडा",
    "description": "फ्लोरिडाची सर्वात मोठी LGBTQ समर्थन संस्था जी सुरक्षित आणि निरोगी शाळांच्या दिशेने, LGBTQ आरोग्य समतोलन, HIV समर्थन, LGBTQ संरक्षण आणि अधिक काम करीत आहे. संस्थेने विविध कार्यक्रमांची वाटचाल केली आहे आणि त्याने ट्रान्सजेंडर आरोग्य देखभाल अनुदानांमध्ये योगदान केलेले समर्थन मिळवले आहे."
  },
  {
    "id": "e5b7c0b6-7106-4426-9809-7d59ebed9ec6",
    "slug": "transhub",
    "externalUrl": "https://www.transhub.org.au/",
    "tags": [
      "transmasculine",
      "non-binary",
      "transfeminine",
      "legal",
      "healthcare",
      "mental-health",
      "social-services",
      "health-providers",
      "community-stories",
      "education-awareness"
    ],
    "address": null,
    "phoneNumber": null,
    "country": "AU",
    "provinceOrState": "NSW",
    "city": null,
    "county": null,
    "latLng": null,
    "email": null,
    "socialMedia": null,
    "title": "TransHub",
    "description": "TransHub हे एक डिजिटल माहिती आणि संसाधन मंच आहे एनएसडब्ल्यूमधील सर्व ट्रान्सांस आणि लिंगविविध लोकांसाठी, त्यांच्या प्रियतमांसाठी, मित्रांसाठी आणि आरोग्य प्रदातांसाठी. हे एक्यूम्युनिटीसाठी गरजेच्या माहिती आणि संसाधनांकडे प्रवेश प्रदान करते ज्यांना त्यांनी वाढत असताना किंवा त्यांच्या मूळ स्वतःच्या तर्फ वाढताना असं उपलब्ध केलेलं नसेल. माहिती हार्मोन्स, शस्त्रक्रिया आणि डॉक्टरांच्या याद्यापासून सामाजिक आणि कायदेशीर मुद्द्यांपर्यंत विस्तृत आहे."
  },
  {
    "id": "e7d26256-017c-4d7e-90d2-30de9386cc03",
    "slug": "twenty10",
    "externalUrl": "https://twenty10.org.au/",
    "tags": [
      "transmasculine",
      "non-binary",
      "transfeminine",
      "social-services",
      "youth-services",
      "support-groups",
      "education-awareness"
    ],
    "address": null,
    "phoneNumber": null,
    "country": "AU",
    "provinceOrState": "NSW",
    "city": "Sydney",
    "county": null,
    "latLng": null,
    "email": null,
    "socialMedia": {
      "instagramUrl": "https://www.instagram.com/twenty10glcs/"
    },
    "title": "Twenty10",
    "description": "Twenty10 ज्याचा चुकीचं पर्यायी नाव GLCS आहे, ते NSW येथील तरुणांना विविध आयुष्य बदलकरच्या सेवा देते, ज्यांची ओळख लेस्बियन, गे, बायसेक्सुअल, ट्रांसजेन्डर किंवा जाती विचलित, इंटरसेक्स, क्विअर, अलिंगी किंवा त्यांच्या ओळखीत संदेह असलेल्यांच्या रूपात आहे. त्यांच्या सेवांमध्ये त्राण आणि संदर्भ, निवास आणि प्रकरण व्यवस्थापन, सल्लागारी, सामाजिक सहाय्य कार्यक्रम आणि LGBTIQA+ समावेशकता प्रशिक्षण आहे"
  },
  {
    "id": "eee5057f-7302-4392-b6aa-add70e3e8556",
    "slug": "transgendermap",
    "externalUrl": "https://transgendermap.com",
    "tags": [
      "transfeminine",
      "non-binary",
      "transmasculine",
      "legal",
      "healthcare",
      "mental-health",
      "social-services",
      "community-stories",
      "education-awareness"
    ],
    "title": "ट्रान्सजेंडर माहिती पत्रिका",
    "description": "Transgendermap.com हे अशांच्या लोकांना व्यावहारिक माहिती व मार्गदर्शन पुरविण्याच्या उद्दिष्टाने तयार केलेले एक ऑनलाईन संसाधन आहे ज्यांना त्यांच्या लिंग परिचयावर प्रश्न असतात किंवा ट्रान्सजेंडर स्पेक्ट्रमवर कोणतीही ठिकाण आहे. वेबसाइटवर ट्रान्सजेंडर टर्मिनोलॉजी समजवणारी, परिवर्तन प्रक्रिया, कायदेशीर मुद्दे, आरोग्यदायी व्यवस्था, व अनेक वैयक्तिक कथांचे विस्तृत विषय आहेत. त्याचे उद्दिष्ट वैयक्तिक यात्रेतील व्यक्तींना 'नकाशा' किंवा लिंग परिचय आणि ट्रान्सजेंडर अनुभवांच्या अनेक पहल्यांच्या मार्गदर्शनास मदत करणे आहे. कृपया सर्वात अद्यतित आणि अचूक माहितीसाठी वास्तविक साइटला भेट द्या."
  },
  {
    "id": "ef7f242d-4d3a-4615-ab35-422dcc90f493",
    "slug": "the-genderaid",
    "externalUrl": "https://genderaid.org/en",
    "tags": [
      "healthcare",
      "education-awareness"
    ],
    "address": "De Boelelaan 1117, 1081 HV Amsterdam, Netherlands",
    "phoneNumber": null,
    "country": "NL",
    "provinceOrState": "NH",
    "city": "Amsterdam",
    "county": "Amsterdam",
    "latLng": [
      52.3346104,
      4.8598083
    ],
    "email": "info@genderaid.org",
    "socialMedia": null,
    "town": "Amsterdam-Zuid",
    "title": "The GenderAid",
    "description": "The GenderAid हे लैंगिक लिंग सर्जरीसाठीच्या निर्णयाच्या मदतीसाठी वापरलेले एक साधन आहे, याचा उद्देश उपचारांच्या पर्यायांविषयी संपूर्ण व विश्वसनीय माहिती पुरविण्याच्या आहे. तो हॉलंडच्या आरोग्य सेवा प्रणालीवर केंद्रित आहे, WPATH च्या मार्गदर्शन निर्देशांशी सामंजस्य साधतो, व त्याचा विकास ट्रान्सजेंडर समुदायाच्या सर्व भागांसाठी झालेला आहे, त्यामध्ये अविभाज्य, लिंगप्रवाही, व लिंगविचित्र व्यक्ती असलेले आहेत."
  },
  {
    "id": "f0aa7c03-8837-40f8-82aa-03beb0ac46cc",
    "slug": "transfolk-of-wa",
    "externalUrl": "https://www.transfolkofwa.org/",
    "tags": [
      "transmasculine",
      "non-binary",
      "transfeminine",
      "legal",
      "healthcare",
      "mental-health",
      "social-services",
      "youth-services",
      "support-groups",
      "parent-family-resources",
      "partner-resources",
      "community-stories",
      "education-awareness"
    ],
    "address": null,
    "phoneNumber": null,
    "country": "AU",
    "provinceOrState": "WA",
    "city": null,
    "county": null,
    "latLng": null,
    "email": null,
    "socialMedia": null,
    "title": "TransFolk of WA",
    "description": "पश्चिम ऑस्ट्रेलियातील ट्रान्सजेंडर लोकांना आणि त्यांच्या प्रियांना मित्रत्पूर्ण समर्थन सेवा. ऑनलईन गट, शिफारसी सेवा आणि संसाधने पुरवणारे आणि विविध कार्यक्रमांची मेजबानी करणारे."
  },
  {
    "id": "f2625d38-e181-4231-8344-214adb6edf36",
    "slug": "transcend-australia",
    "externalUrl": "https://transcend.org.au/",
    "tags": [
      "support-groups",
      "parent-family-resources",
      "education-awareness"
    ],
    "address": null,
    "phoneNumber": null,
    "country": "AU",
    "provinceOrState": null,
    "city": null,
    "county": null,
    "latLng": null,
    "email": null,
    "socialMedia": null,
    "title": "Transcend Australia",
    "description": "Transcend Australia च्या उद्देशाची मदत करण्याची, स्वीकारण देण्याची आणि विविध लिंगी बाल आणि त्यांच्या कुटुंबीयांची आणि त्यांच्या संरक्षकांची आणखीन जीवन प्रस्थापन करण्याची आहे. ते ऑस्ट्रेलिया भरतील कुटुंबांना माहिती, मदत आणि संदर्भांची पुरवठा करतात आणि विविध लिंगी बाल आणि तरुणांना सशक्त करण्याचे काम करतात."
  },
  {
    "id": "f48634db-fe71-426c-be84-622b3282bad7",
    "slug": "planned-parenthood",
    "externalUrl": "https://www.plannedparenthood.org/",
    "tags": [
      "healthcare",
      "mental-health",
      "education-awareness"
    ],
    "address": null,
    "phoneNumber": "1-800-230-7526",
    "country": "US",
    "provinceOrState": null,
    "city": null,
    "county": null,
    "latLng": null,
    "email": null,
    "socialMedia": null,
    "title": "नियोजित पालकत्व",
    "description": "नियोजित पालकत्व मिलियनांच्या तुलनेत कोणत्याही व्यक्तीला महत्वाची प्रजनन आरोग्य सेवा, लैंगिक शिक्षण, व माहिती प्रदान करते. सेवा म्हणजे गर्भपात, गर्भनिरोधक, STD चाचणी आणि उपचार, गल्ली हार्मोन थेरेपी, व अधिक. ऑनलाइन आणि टेलीहेल्थ अॅपॉईंटमेंट उपलब्ध आहेत."
  },
  {
    "id": "f596a8bb-1a7d-4b86-a865-c6d6a17984bc",
    "slug": "rfsl-swedish-federation-lgbtq-rights",
    "externalUrl": "https://www.rfsl.se/",
    "tags": [
      "transmasculine",
      "transfeminine",
      "non-binary",
      "legal",
      "healthcare",
      "mental-health",
      "social-services",
      "education-awareness",
      "support-groups"
    ],
    "address": null,
    "phoneNumber": null,
    "country": "SE",
    "provinceOrState": null,
    "city": null,
    "county": null,
    "latLng": null,
    "email": null,
    "socialMedia": {},
    "title": "RFSL - समलैंगिक, समलैंगी, द्वैलिंगी, लैंगिक विद्यमान क्षेत्रातील आणि क्विअर अधिकारांसाठी स्वीडिश संघटना",
    "description": "RFSL ही स्वीडनी संघटना असून, ती LGBTQ अधिकारांसाठी काम करते. त्यांनी लैंगिक विद्यमान क्षेत्रातील समुदायासाठी महत्त्वाच्या संसाधने, समुदाय समर्थन, शिक्षण आणि जागरूकता, कायदेशीर मार्गदर्शन, आरोग्य सेवा, आणि अधिक प्रदान केलेली आहेत. RFSL म्हणजेच LGBTQ अधिकार अंतरराष्ट्रीय पातळीवर संवर्धन करते."
  },
  {
    "id": "f8b46156-9e3c-4347-aa8a-1df0f89e8f25",
    "slug": "apotheek-all-about-medication",
    "externalUrl": "https://www.apotheek.nl/",
    "tags": [
      "healthcare",
      "education-awareness"
    ],
    "address": null,
    "phoneNumber": null,
    "country": "NL",
    "provinceOrState": null,
    "city": null,
    "county": null,
    "latLng": null,
    "email": null,
    "socialMedia": null,
    "title": "Apotheek.nl - सर्व मेडिकेशन विषयी",
    "description": "विविध औषधांबद्दल विश्वसनीय माहिती प्रदान करणार्या संसाधनांची सायट. या साइटमध्ये व्हिडिओ, आरोग्य संचालनातील चालू घडामोडी, लसीकरण, कोरोनाव्हायरस, आणि फार्मेसी केअर यांची माहिती असते. ती डच भाषेत माहिती देते आणि युक्रेनियन शरणार्थ्यांसाठी 50 मुख्य औषधांचे भाषांतर करते."
  },
  {
    "id": "fc8a7875-84dd-4df5-96ec-8aca153c8ea6",
    "slug": "trans-families-home",
    "externalUrl": "https://transfamilies.org",
    "tags": [
      "transmasculine",
      "non-binary",
      "transfeminine",
      "parent-family-resources",
      "support-groups",
      "education-awareness"
    ],
    "email": null,
    "phoneNumber": null,
    "address": null,
    "socialMedia": null,
    "title": "संवेदनशील कुटुंब",
    "description": "संवेदनशील कुटुंबांनी आशावाद जोखीम घेतला, समजून घेण्याची क्षमता वाढवली, आणि संवेदनशील आणि लिंगभेदी मुलांच्या मदतीसाठी दृश्यमान मार्ग तयार केला. आम्ही संसाधने पुरवतो, कार्यक्रमे योजित करतो आणि कुटुंबांची मदत करणाऱ्या समूहांशी संपर्क साधतो."
  }
]