{
  "id": "aac7385e-58e6-4839-be0e-b637b1021437",
  "title": "Bradbury-Sullivan LGBT Community Center",
  "description": "Bradbury-Sullivan LGBT Community Center provides a vibrant, inclusive space in Pennsylvania's Lehigh Valley for all of the region's LGBTQ+ residents. It offers community programming, addressing barriers to care through its health programs, organizes annual Pride festival and works towards increasing equity through its LGBTQ+ Education Institute.",
  "slug": "bradbury-sullivan-lgbt-community-center",
  "externalUrl": "https://www.bradburysullivancenter.org/",
  "tags": [
    "healthcare",
    "education-awareness",
    "social-services",
    "support-groups"
  ],
  "address": "522 W Maple St, Allentown, PA 18101, USA",
  "phoneNumber": "(610) 347-9988",
  "country": "US",
  "provinceOrState": "PA",
  "city": "Allentown",
  "county": "Lehigh County",
  "latLng": [
    40.60245,
    -75.46774780000001
  ],
  "email": null,
  "socialMedia": null
}