{
  "i18n": {
    "en-US": {
      "title": "One Medical - Exceptional Primary Care",
      "description": "One Medical offers exceptional primary care facilities and personalized attention to all patients, including the transgender community. The office schedules long appointments for in-depth discussions and has multiple services covering everything from chronic care to mental health issues. It offers compassionate care, recognizing the unique medical and emotional needs of transgender individuals. Practitioners are experienced in handling sensitive matters such as hormone replacement therapy, post-surgery care, and transgender-specific mental health care."
    }
  },
  "slug": "one-medical-exceptional-primary-care-new-york",
  "tags": [
    "healthcare",
    "informed-consent-clinic"
  ],
  "organizationType": [
    "local-office",
    "informed-consent-clinic"
  ],
  "id": "09ee5cba-82db-4241-9900-4141237d5005",
  "externalUrl": "https://www.onemedical.com/locations/nyc/408w14th/?utm_source=google&utm_medium=organic&utm_campaign=localseo",
  "address": "408 W 14th St #201, New York, NY 10014, USA",
  "phoneNumber": "+1 888-663-6331",
  "socialMedia": {
    "googleMapsUrl": "https://maps.google.com/?cid=5356733190390784243"
  },
  "country": "US",
  "provinceOrState": "NY",
  "county": "New York County",
  "city": "New York",
  "town": "Manhattan",
  "latLng": [
    40.7409206,
    -74.0060163
  ]
}